{
  "extraction_info": {
    "timestamp": "2025-08-06T03:09:00.428Z",
    "page_url": "https://www.coles.com.au/browse/dairy-eggs-fridge?page=32",
    "category": "dairy-eggs-fridge",
    "page_number": 32,
    "selector_set_used": "high_confidence",
    "total_products": 58,
    "total_elements_found": 58
  },
  "products": [
    {
      "title": "Youfoodz Youjuice Blue Tropics | 350mL",
      "current_price": 3.9,
      "original_price": null,
      "discount_percentage": null,
      "discount_amount": null,
      "image_url": "https://www.coles.com.au/_next/image?url=https%3A%2F%2Fcdn.productimages.coles.com.au%2Fproductimages%2F6%2F6284148.jpg&w=640&q=90",
      "product_url": "https://www.coles.com.au/product/youfoodz-youjuice-blue-tropics-350ml-6284148",
      "category": "dairy-eggs-fridge",
      "brand": null,
      "weight_size": null,
      "per_unit_price": "$11.14 per 1L",
      "rating": null,
      "review_count": null,
      "in_stock": true,
      "is_on_sale": false,
      "scraped_at": "2025-08-06T03:09:00.428Z",
      "page_number": 32,
      "source_url": "https://www.coles.com.au/browse/dairy-eggs-fridge?page=32",
      "is_sponsored": null
    },
    {
      "title": "Latina Fresh Beef Ravioli Pasta 4 Serve | 625g",
      "current_price": 11,
      "original_price": null,
      "discount_percentage": null,
      "discount_amount": null,
      "image_url": "https://www.coles.com.au/_next/image?url=https%3A%2F%2Fcdn.productimages.coles.com.au%2Fproductimages%2F5%2F5404110.jpg&w=640&q=90",
      "product_url": "https://www.coles.com.au/product/latina-fresh-beef-ravioli-pasta-4-serve-625g-5404110",
      "category": "dairy-eggs-fridge",
      "brand": null,
      "weight_size": null,
      "per_unit_price": "$1.76 per 100g",
      "rating": null,
      "review_count": null,
      "in_stock": true,
      "is_on_sale": false,
      "scraped_at": "2025-08-06T03:09:00.428Z",
      "page_number": 32,
      "source_url": "https://www.coles.com.au/browse/dairy-eggs-fridge?page=32",
      "is_sponsored": true
    },
    {
      "title": "Devondale Regular Pat Butter | 250g",
      "current_price": 4.6,
      "original_price": null,
      "discount_percentage": null,
      "discount_amount": null,
      "image_url": "https://www.coles.com.au/_next/image?url=https%3A%2F%2Fcdn.productimages.coles.com.au%2Fproductimages%2F1%2F1778617.jpg&w=640&q=90",
      "product_url": "https://www.coles.com.au/product/devondale-regular-pat-butter-250g-1778617",
      "category": "dairy-eggs-fridge",
      "brand": null,
      "weight_size": null,
      "per_unit_price": "$1.84 per 100gWas $5.30 on Jul 2025",
      "rating": null,
      "review_count": null,
      "in_stock": true,
      "is_on_sale": false,
      "scraped_at": "2025-08-06T03:09:00.428Z",
      "page_number": 32,
      "source_url": "https://www.coles.com.au/browse/dairy-eggs-fridge?page=32",
      "is_sponsored": true
    },
    {
      "title": "Devondale Dairy Soft DY Blend Tub Regular | 500g",
      "current_price": 6.5,
      "original_price": null,
      "discount_percentage": null,
      "discount_amount": null,
      "image_url": "https://www.coles.com.au/_next/image?url=https%3A%2F%2Fcdn.productimages.coles.com.au%2Fproductimages%2F5%2F5017500.jpg&w=640&q=90",
      "product_url": "https://www.coles.com.au/product/devondale-dairy-soft-dy-blend-tub-regular-500g-5017500",
      "category": "dairy-eggs-fridge",
      "brand": null,
      "weight_size": null,
      "per_unit_price": "$1.30 per 100g | Was $7.50",
      "rating": null,
      "review_count": null,
      "in_stock": true,
      "is_on_sale": false,
      "scraped_at": "2025-08-06T03:09:00.428Z",
      "page_number": 32,
      "source_url": "https://www.coles.com.au/browse/dairy-eggs-fridge?page=32",
      "is_sponsored": true
    },
    {
      "title": "Obela Classic Tzatziki | 220g",
      "current_price": 5.5,
      "original_price": null,
      "discount_percentage": null,
      "discount_amount": null,
      "image_url": "https://www.coles.com.au/_next/image?url=https%3A%2F%2Fcdn.productimages.coles.com.au%2Fproductimages%2F2%2F2882851.jpg&w=640&q=90",
      "product_url": "https://www.coles.com.au/product/obela-classic-tzatziki-220g-2882851",
      "category": "dairy-eggs-fridge",
      "brand": null,
      "weight_size": null,
      "per_unit_price": "$2.50 per 100g",
      "rating": null,
      "review_count": null,
      "in_stock": true,
      "is_on_sale": false,
      "scraped_at": "2025-08-06T03:09:00.428Z",
      "page_number": 32,
      "source_url": "https://www.coles.com.au/browse/dairy-eggs-fridge?page=32",
      "is_sponsored": true
    },
    {
      "title": "Latina Fresh Beef Ravioli Pasta | 375g",
      "current_price": 5.6,
      "original_price": null,
      "discount_percentage": null,
      "discount_amount": null,
      "image_url": "https://www.coles.com.au/_next/image?url=https%3A%2F%2Fcdn.productimages.coles.com.au%2Fproductimages%2F5%2F5051858.jpg&w=640&q=90",
      "product_url": "https://www.coles.com.au/product/latina-fresh-beef-ravioli-pasta-375g-5051858",
      "category": "dairy-eggs-fridge",
      "brand": null,
      "weight_size": null,
      "per_unit_price": "$1.49 per 100g | Was $8.00",
      "rating": null,
      "review_count": null,
      "in_stock": true,
      "is_on_sale": false,
      "scraped_at": "2025-08-06T03:09:00.428Z",
      "page_number": 32,
      "source_url": "https://www.coles.com.au/browse/dairy-eggs-fridge?page=32",
      "is_sponsored": true
    },
    {
      "title": "Red Rock Deli Dip Roasted Capsicum Pecorino Cashew & Basil | 135g",
      "current_price": 5,
      "original_price": null,
      "discount_percentage": null,
      "discount_amount": null,
      "image_url": "https://www.coles.com.au/_next/image?url=https%3A%2F%2Fcdn.productimages.coles.com.au%2Fproductimages%2F7%2F7083120.jpg&w=640&q=90",
      "product_url": "https://www.coles.com.au/product/red-rock-deli-dip-roasted-capsicum-pecorino-cashew-and-basil-135g-7083120",
      "category": "dairy-eggs-fridge",
      "brand": null,
      "weight_size": null,
      "per_unit_price": "$3.70 per 100g",
      "rating": null,
      "review_count": null,
      "in_stock": true,
      "is_on_sale": false,
      "scraped_at": "2025-08-06T03:09:00.428Z",
      "page_number": 32,
      "source_url": "https://www.coles.com.au/browse/dairy-eggs-fridge?page=32",
      "is_sponsored": true
    },
    {
      "title": "Riverina Fetta Greek Style | 200g",
      "current_price": 4.7,
      "original_price": null,
      "discount_percentage": null,
      "discount_amount": null,
      "image_url": "https://www.coles.com.au/_next/image?url=https%3A%2F%2Fcdn.productimages.coles.com.au%2Fproductimages%2F4%2F4360879.jpg&w=640&q=90",
      "product_url": "https://www.coles.com.au/product/riverina-fetta-greek-style-200g-4360879",
      "category": "dairy-eggs-fridge",
      "brand": null,
      "weight_size": null,
      "per_unit_price": "$23.50 per 1kgWas $5.30 on Jul 2025",
      "rating": null,
      "review_count": null,
      "in_stock": true,
      "is_on_sale": false,
      "scraped_at": "2025-08-06T03:09:00.428Z",
      "page_number": 32,
      "source_url": "https://www.coles.com.au/browse/dairy-eggs-fridge?page=32",
      "is_sponsored": true
    },
    {
      "title": "V2 Burger Beef 4pk 452g | 452GRAM",
      "current_price": 9,
      "original_price": null,
      "discount_percentage": null,
      "discount_amount": null,
      "image_url": "https://www.coles.com.au/_next/image?url=https%3A%2F%2Fcdn.productimages.coles.com.au%2Fproductimages%2F8%2F8851668.jpg&w=640&q=90",
      "product_url": "https://www.coles.com.au/product/v2-burger-beef-4pk-452g-452gram-8851668",
      "category": "dairy-eggs-fridge",
      "brand": null,
      "weight_size": null,
      "per_unit_price": "$1.99 per 100g | Was $10.00",
      "rating": null,
      "review_count": null,
      "in_stock": true,
      "is_on_sale": false,
      "scraped_at": "2025-08-06T03:09:00.428Z",
      "page_number": 32,
      "source_url": "https://www.coles.com.au/browse/dairy-eggs-fridge?page=32",
      "is_sponsored": true
    },
    {
      "title": "Danone Activia Probiotics No Added Sugar Yoghurt Mixed Berries 4x125g | 500g",
      "current_price": 5.75,
      "original_price": null,
      "discount_percentage": null,
      "discount_amount": null,
      "image_url": "https://www.coles.com.au/_next/image?url=https%3A%2F%2Fcdn.productimages.coles.com.au%2Fproductimages%2F8%2F8169435.jpg&w=640&q=90",
      "product_url": "https://www.coles.com.au/product/danone-activia-probiotics-no-added-sugar-yoghurt-mixed-berries-4x125g-500g-8169435",
      "category": "dairy-eggs-fridge",
      "brand": null,
      "weight_size": null,
      "per_unit_price": "$1.15 per 100g",
      "rating": null,
      "review_count": null,
      "in_stock": true,
      "is_on_sale": false,
      "scraped_at": "2025-08-06T03:09:00.428Z",
      "page_number": 32,
      "source_url": "https://www.coles.com.au/browse/dairy-eggs-fridge?page=32",
      "is_sponsored": true
    },
    {
      "title": "Danone Activia Probiotics No Added Sugar Yoghurt Mango 4x125g | 500g",
      "current_price": 5.75,
      "original_price": null,
      "discount_percentage": null,
      "discount_amount": null,
      "image_url": "https://www.coles.com.au/_next/image?url=https%3A%2F%2Fcdn.productimages.coles.com.au%2Fproductimages%2F8%2F8872089.jpg&w=640&q=90",
      "product_url": "https://www.coles.com.au/product/danone-activia-probiotics-no-added-sugar-yoghurt-mango-4x125g-500g-8872089",
      "category": "dairy-eggs-fridge",
      "brand": null,
      "weight_size": null,
      "per_unit_price": "$1.15 per 100g",
      "rating": null,
      "review_count": null,
      "in_stock": true,
      "is_on_sale": false,
      "scraped_at": "2025-08-06T03:09:00.428Z",
      "page_number": 32,
      "source_url": "https://www.coles.com.au/browse/dairy-eggs-fridge?page=32",
      "is_sponsored": true
    },
    {
      "title": "Emma & Tom's Limited Edition | 350mL",
      "current_price": 4.2,
      "original_price": null,
      "discount_percentage": null,
      "discount_amount": null,
      "image_url": "https://www.coles.com.au/_next/image?url=https%3A%2F%2Fcdn.productimages.coles.com.au%2Fproductimages%2F6%2F6313166.jpg&w=640&q=90",
      "product_url": "https://www.coles.com.au/product/emma-and-tom's-limited-edition-350ml-6313166",
      "category": "dairy-eggs-fridge",
      "brand": null,
      "weight_size": null,
      "per_unit_price": "$12.00 per 1L",
      "rating": null,
      "review_count": null,
      "in_stock": true,
      "is_on_sale": false,
      "scraped_at": "2025-08-06T03:09:00.428Z",
      "page_number": 32,
      "source_url": "https://www.coles.com.au/browse/dairy-eggs-fridge?page=32",
      "is_sponsored": null
    },
    {
      "title": "Emma & Tom's Limited Edition | 450mL",
      "current_price": 4.2,
      "original_price": null,
      "discount_percentage": null,
      "discount_amount": null,
      "image_url": "https://www.coles.com.au/_next/image?url=https%3A%2F%2Fcdn.productimages.coles.com.au%2Fproductimages%2F6%2F6313188.jpg&w=640&q=90",
      "product_url": "https://www.coles.com.au/product/emma-and-tom's-limited-edition-450ml-6313188",
      "category": "dairy-eggs-fridge",
      "brand": null,
      "weight_size": null,
      "per_unit_price": "$9.33 per 1L",
      "rating": null,
      "review_count": null,
      "in_stock": true,
      "is_on_sale": false,
      "scraped_at": "2025-08-06T03:09:00.428Z",
      "page_number": 32,
      "source_url": "https://www.coles.com.au/browse/dairy-eggs-fridge?page=32",
      "is_sponsored": null
    },
    {
      "title": "Coles Simply Regular Spread | 500g",
      "current_price": 2.2,
      "original_price": null,
      "discount_percentage": null,
      "discount_amount": null,
      "image_url": "https://www.coles.com.au/_next/image?url=https%3A%2F%2Fcdn.productimages.coles.com.au%2Fproductimages%2F6%2F6319071.jpg&w=640&q=90",
      "product_url": "https://www.coles.com.au/product/coles-simply-regular-spread-500g-6319071",
      "category": "dairy-eggs-fridge",
      "brand": null,
      "weight_size": null,
      "per_unit_price": "$0.44 per 100g",
      "rating": null,
      "review_count": null,
      "in_stock": true,
      "is_on_sale": false,
      "scraped_at": "2025-08-06T03:09:00.428Z",
      "page_number": 32,
      "source_url": "https://www.coles.com.au/browse/dairy-eggs-fridge?page=32",
      "is_sponsored": null
    },
    {
      "title": "Coles Unsweetened Oat Milk | 1L",
      "current_price": 2,
      "original_price": null,
      "discount_percentage": null,
      "discount_amount": null,
      "image_url": "https://www.coles.com.au/_next/image?url=https%3A%2F%2Fcdn.productimages.coles.com.au%2Fproductimages%2F6%2F6337674.jpg&w=640&q=90",
      "product_url": "https://www.coles.com.au/product/coles-unsweetened-oat-milk-1l-6337674",
      "category": "dairy-eggs-fridge",
      "brand": null,
      "weight_size": null,
      "per_unit_price": "$2.00 per 1L",
      "rating": null,
      "review_count": null,
      "in_stock": true,
      "is_on_sale": false,
      "scraped_at": "2025-08-06T03:09:00.428Z",
      "page_number": 32,
      "source_url": "https://www.coles.com.au/browse/dairy-eggs-fridge?page=32",
      "is_sponsored": null
    },
    {
      "title": "Good Yolk Co Cage Free Eggs 12 Pack | 700g",
      "current_price": 6.5,
      "original_price": null,
      "discount_percentage": null,
      "discount_amount": null,
      "image_url": "https://www.coles.com.au/_next/image?url=https%3A%2F%2Fcdn.productimages.coles.com.au%2Fproductimages%2F6%2F6339498.jpg&w=640&q=90",
      "product_url": "https://www.coles.com.au/product/good-yolk-co-cage-free-eggs-12-pack-700g-6339498",
      "category": "dairy-eggs-fridge",
      "brand": null,
      "weight_size": null,
      "per_unit_price": "$0.93 per 100g",
      "rating": null,
      "review_count": null,
      "in_stock": true,
      "is_on_sale": false,
      "scraped_at": "2025-08-06T03:09:00.428Z",
      "page_number": 32,
      "source_url": "https://www.coles.com.au/browse/dairy-eggs-fridge?page=32",
      "is_sponsored": null
    },
    {
      "title": "Good Yolk Co Cage Free Eggs 12 Pack | 600g",
      "current_price": 6.2,
      "original_price": null,
      "discount_percentage": null,
      "discount_amount": null,
      "image_url": "https://www.coles.com.au/_next/image?url=https%3A%2F%2Fcdn.productimages.coles.com.au%2Fproductimages%2F6%2F6339512.jpg&w=640&q=90",
      "product_url": "https://www.coles.com.au/product/good-yolk-co-cage-free-eggs-12-pack-600g-6339512",
      "category": "dairy-eggs-fridge",
      "brand": null,
      "weight_size": null,
      "per_unit_price": "$1.03 per 100g",
      "rating": null,
      "review_count": null,
      "in_stock": true,
      "is_on_sale": false,
      "scraped_at": "2025-08-06T03:09:00.428Z",
      "page_number": 32,
      "source_url": "https://www.coles.com.au/browse/dairy-eggs-fridge?page=32",
      "is_sponsored": null
    },
    {
      "title": "Sunrise Free Range Eggs 12 Pack | 700g",
      "current_price": 8.2,
      "original_price": null,
      "discount_percentage": null,
      "discount_amount": null,
      "image_url": "https://www.coles.com.au/_next/image?url=https%3A%2F%2Fcdn.productimages.coles.com.au%2Fproductimages%2F6%2F6339534.jpg&w=640&q=90",
      "product_url": "https://www.coles.com.au/product/sunrise-free-range-eggs-12-pack-700g-6339534",
      "category": "dairy-eggs-fridge",
      "brand": null,
      "weight_size": null,
      "per_unit_price": "$1.17 per 100g",
      "rating": null,
      "review_count": null,
      "in_stock": true,
      "is_on_sale": false,
      "scraped_at": "2025-08-06T03:09:00.428Z",
      "page_number": 32,
      "source_url": "https://www.coles.com.au/browse/dairy-eggs-fridge?page=32",
      "is_sponsored": null
    },
    {
      "title": "Sunrise Free Range Eggs 12 Pack | 600g",
      "current_price": 5,
      "original_price": null,
      "discount_percentage": null,
      "discount_amount": null,
      "image_url": "https://www.coles.com.au/_next/image?url=https%3A%2F%2Fcdn.productimages.coles.com.au%2Fproductimages%2F6%2F6344512.jpg&w=640&q=90",
      "product_url": "https://www.coles.com.au/product/sunrise-free-range-eggs-12-pack-600g-6344512",
      "category": "dairy-eggs-fridge",
      "brand": null,
      "weight_size": null,
      "per_unit_price": "$0.83 per 100g",
      "rating": null,
      "review_count": null,
      "in_stock": true,
      "is_on_sale": false,
      "scraped_at": "2025-08-06T03:09:00.428Z",
      "page_number": 32,
      "source_url": "https://www.coles.com.au/browse/dairy-eggs-fridge?page=32",
      "is_sponsored": null
    },
    {
      "title": "Perfect Italiano Dairy Cheese Grated Mozzarella:mozzare ... 450g",
      "current_price": 9.5,
      "original_price": null,
      "discount_percentage": null,
      "discount_amount": null,
      "image_url": "https://www.coles.com.au/_next/image?url=https%3A%2F%2Fcdn.productimages.coles.com.au%2Fproductimages%2F6%2F63816.jpg&w=640&q=90",
      "product_url": "https://www.coles.com.au/product/perfect-italiano-dairy-cheese-grated-mozzarella:mozzarella-450g-63816",
      "category": "dairy-eggs-fridge",
      "brand": null,
      "weight_size": null,
      "per_unit_price": "$21.11 per 1kg",
      "rating": null,
      "review_count": null,
      "in_stock": true,
      "is_on_sale": false,
      "scraped_at": "2025-08-06T03:09:00.428Z",
      "page_number": 32,
      "source_url": "https://www.coles.com.au/browse/dairy-eggs-fridge?page=32",
      "is_sponsored": null
    },
    {
      "title": "Latina Fresh Kids Mini Ravioli Pasta Beef & Vegetable | 200g",
      "current_price": 6,
      "original_price": null,
      "discount_percentage": null,
      "discount_amount": null,
      "image_url": "https://www.coles.com.au/_next/image?url=https%3A%2F%2Fcdn.productimages.coles.com.au%2Fproductimages%2F6%2F6393915.jpg&w=640&q=90",
      "product_url": "https://www.coles.com.au/product/latina-fresh-kids-mini-ravioli-pasta-beef-and-vegetable-200g-6393915",
      "category": "dairy-eggs-fridge",
      "brand": null,
      "weight_size": null,
      "per_unit_price": "$3.00 per 100g",
      "rating": null,
      "review_count": null,
      "in_stock": true,
      "is_on_sale": false,
      "scraped_at": "2025-08-06T03:09:00.428Z",
      "page_number": 32,
      "source_url": "https://www.coles.com.au/browse/dairy-eggs-fridge?page=32",
      "is_sponsored": null
    },
    {
      "title": "Latina Fresh Kids Mini Ravioli Pasta Cheese & Vegetable | 200g",
      "current_price": 6,
      "original_price": null,
      "discount_percentage": null,
      "discount_amount": null,
      "image_url": "https://www.coles.com.au/_next/image?url=https%3A%2F%2Fcdn.productimages.coles.com.au%2Fproductimages%2F6%2F6393926.jpg&w=640&q=90",
      "product_url": "https://www.coles.com.au/product/latina-fresh-kids-mini-ravioli-pasta-cheese-and-vegetable-200g-6393926",
      "category": "dairy-eggs-fridge",
      "brand": null,
      "weight_size": null,
      "per_unit_price": "$3.00 per 100g",
      "rating": null,
      "review_count": null,
      "in_stock": true,
      "is_on_sale": false,
      "scraped_at": "2025-08-06T03:09:00.428Z",
      "page_number": 32,
      "source_url": "https://www.coles.com.au/browse/dairy-eggs-fridge?page=32",
      "is_sponsored": null
    },
    {
      "title": "25 Degrees South Prosciutto & Ricotta Ravioli | 325g",
      "current_price": 9,
      "original_price": null,
      "discount_percentage": null,
      "discount_amount": null,
      "image_url": "https://www.coles.com.au/_next/image?url=https%3A%2F%2Fcdn.productimages.coles.com.au%2Fproductimages%2F6%2F6399591.jpg&w=640&q=90",
      "product_url": "https://www.coles.com.au/product/25-degrees-south-prosciutto-and-ricotta-ravioli-325g-6399591",
      "category": "dairy-eggs-fridge",
      "brand": null,
      "weight_size": null,
      "per_unit_price": "$2.77 per 100g",
      "rating": null,
      "review_count": null,
      "in_stock": true,
      "is_on_sale": false,
      "scraped_at": "2025-08-06T03:09:00.428Z",
      "page_number": 32,
      "source_url": "https://www.coles.com.au/browse/dairy-eggs-fridge?page=32",
      "is_sponsored": null
    },
    {
      "title": "Flora Plant Based Thickened Cream 31% | 500mL",
      "current_price": 6.5,
      "original_price": null,
      "discount_percentage": null,
      "discount_amount": null,
      "image_url": "https://www.coles.com.au/_next/image?url=https%3A%2F%2Fcdn.productimages.coles.com.au%2Fproductimages%2F6%2F6413590.jpg&w=640&q=90",
      "product_url": "https://www.coles.com.au/product/flora-plant-based-thickened-cream-31percent-500ml-6413590",
      "category": "dairy-eggs-fridge",
      "brand": null,
      "weight_size": null,
      "per_unit_price": "$1.30 per 100mL",
      "rating": null,
      "review_count": null,
      "in_stock": true,
      "is_on_sale": false,
      "scraped_at": "2025-08-06T03:09:00.428Z",
      "page_number": 32,
      "source_url": "https://www.coles.com.au/browse/dairy-eggs-fridge?page=32",
      "is_sponsored": null
    },
    {
      "title": "South Cape Greek Style Fetta | 200g",
      "current_price": 6.5,
      "original_price": null,
      "discount_percentage": null,
      "discount_amount": null,
      "image_url": "https://www.coles.com.au/_next/image?url=https%3A%2F%2Fcdn.productimages.coles.com.au%2Fproductimages%2F6%2F6416861.jpg&w=640&q=90",
      "product_url": "https://www.coles.com.au/product/south-cape-greek-style-fetta-200g-6416861",
      "category": "dairy-eggs-fridge",
      "brand": null,
      "weight_size": null,
      "per_unit_price": "$32.50 per 1kg",
      "rating": null,
      "review_count": null,
      "in_stock": true,
      "is_on_sale": false,
      "scraped_at": "2025-08-06T03:09:00.428Z",
      "page_number": 32,
      "source_url": "https://www.coles.com.au/browse/dairy-eggs-fridge?page=32",
      "is_sponsored": null
    },
    {
      "title": "South Cape Reduced Fat Greek Style Fetta | 200g",
      "current_price": 6.5,
      "original_price": null,
      "discount_percentage": null,
      "discount_amount": null,
      "image_url": "https://www.coles.com.au/_next/image?url=https%3A%2F%2Fcdn.productimages.coles.com.au%2Fproductimages%2F6%2F6416883.jpg&w=640&q=90",
      "product_url": "https://www.coles.com.au/product/south-cape-reduced-fat-greek-style-fetta-200g-6416883",
      "category": "dairy-eggs-fridge",
      "brand": null,
      "weight_size": null,
      "per_unit_price": "$32.50 per 1kg",
      "rating": null,
      "review_count": null,
      "in_stock": true,
      "is_on_sale": false,
      "scraped_at": "2025-08-06T03:09:00.428Z",
      "page_number": 32,
      "source_url": "https://www.coles.com.au/browse/dairy-eggs-fridge?page=32",
      "is_sponsored": null
    },
    {
      "title": "Dairy Farmers Pure Cream | 500mL",
      "current_price": 5.5,
      "original_price": null,
      "discount_percentage": null,
      "discount_amount": null,
      "image_url": "https://www.coles.com.au/_next/image?url=https%3A%2F%2Fcdn.productimages.coles.com.au%2Fproductimages%2F6%2F6436359.jpg&w=640&q=90",
      "product_url": "https://www.coles.com.au/product/dairy-farmers-pure-cream-500ml-6436359",
      "category": "dairy-eggs-fridge",
      "brand": null,
      "weight_size": null,
      "per_unit_price": "$1.10 per 100mL",
      "rating": null,
      "review_count": null,
      "in_stock": true,
      "is_on_sale": false,
      "scraped_at": "2025-08-06T03:09:00.428Z",
      "page_number": 32,
      "source_url": "https://www.coles.com.au/browse/dairy-eggs-fridge?page=32",
      "is_sponsored": null
    },
    {
      "title": "Annie's Orchard Unsweetened Almond Milk | 1L",
      "current_price": 3.3,
      "original_price": null,
      "discount_percentage": null,
      "discount_amount": null,
      "image_url": "https://www.coles.com.au/_next/image?url=https%3A%2F%2Fcdn.productimages.coles.com.au%2Fproductimages%2F6%2F6450203.jpg&w=640&q=90",
      "product_url": "https://www.coles.com.au/product/annie's-orchard-unsweetened-almond-milk-1l-6450203",
      "category": "dairy-eggs-fridge",
      "brand": null,
      "weight_size": null,
      "per_unit_price": "$3.30 per 1L",
      "rating": null,
      "review_count": null,
      "in_stock": true,
      "is_on_sale": false,
      "scraped_at": "2025-08-06T03:09:00.428Z",
      "page_number": 32,
      "source_url": "https://www.coles.com.au/browse/dairy-eggs-fridge?page=32",
      "is_sponsored": null
    },
    {
      "title": "Annie's Orchard Unsweetened Oat Milk | 1L",
      "current_price": 3.3,
      "original_price": null,
      "discount_percentage": null,
      "discount_amount": null,
      "image_url": "https://www.coles.com.au/_next/image?url=https%3A%2F%2Fcdn.productimages.coles.com.au%2Fproductimages%2F6%2F6450214.jpg&w=640&q=90",
      "product_url": "https://www.coles.com.au/product/annie's-orchard-unsweetened-oat-milk-1l-6450214",
      "category": "dairy-eggs-fridge",
      "brand": null,
      "weight_size": null,
      "per_unit_price": "$3.30 per 1L",
      "rating": null,
      "review_count": null,
      "in_stock": true,
      "is_on_sale": false,
      "scraped_at": "2025-08-06T03:09:00.428Z",
      "page_number": 32,
      "source_url": "https://www.coles.com.au/browse/dairy-eggs-fridge?page=32",
      "is_sponsored": null
    },
    {
      "title": "East Coast Sustainable Organic Full Cream Milk | 2L",
      "current_price": 6.9,
      "original_price": null,
      "discount_percentage": null,
      "discount_amount": null,
      "image_url": "https://www.coles.com.au/_next/image?url=https%3A%2F%2Fcdn.productimages.coles.com.au%2Fproductimages%2F6%2F6450917.jpg&w=640&q=90",
      "product_url": "https://www.coles.com.au/product/east-coast-sustainable-organic-full-cream-milk-2l-6450917",
      "category": "dairy-eggs-fridge",
      "brand": null,
      "weight_size": null,
      "per_unit_price": "$3.45 per 1L",
      "rating": null,
      "review_count": null,
      "in_stock": true,
      "is_on_sale": false,
      "scraped_at": "2025-08-06T03:09:00.428Z",
      "page_number": 32,
      "source_url": "https://www.coles.com.au/browse/dairy-eggs-fridge?page=32",
      "is_sponsored": null
    },
    {
      "title": "Australia's Own Smooth As Oat Milk | 1L",
      "current_price": 2.5,
      "original_price": null,
      "discount_percentage": null,
      "discount_amount": null,
      "image_url": "https://www.coles.com.au/_next/image?url=https%3A%2F%2Fcdn.productimages.coles.com.au%2Fproductimages%2F6%2F6494515.jpg&w=640&q=90",
      "product_url": "https://www.coles.com.au/product/australia's-own-smooth-as-oat-milk-1l-6494515",
      "category": "dairy-eggs-fridge",
      "brand": null,
      "weight_size": null,
      "per_unit_price": "$2.50 per 1LWas $3.00 on May 2025",
      "rating": null,
      "review_count": null,
      "in_stock": true,
      "is_on_sale": false,
      "scraped_at": "2025-08-06T03:09:00.428Z",
      "page_number": 32,
      "source_url": "https://www.coles.com.au/browse/dairy-eggs-fridge?page=32",
      "is_sponsored": null
    },
    {
      "title": "Sanitarium So Good Barista Soy UHT | 1L",
      "current_price": 3,
      "original_price": null,
      "discount_percentage": null,
      "discount_amount": null,
      "image_url": "https://www.coles.com.au/_next/image?url=https%3A%2F%2Fcdn.productimages.coles.com.au%2Fproductimages%2F6%2F6501290.jpg&w=640&q=90",
      "product_url": "https://www.coles.com.au/product/sanitarium-so-good-barista-soy-uht-1l-6501290",
      "category": "dairy-eggs-fridge",
      "brand": null,
      "weight_size": null,
      "per_unit_price": "$3.00 per 1L",
      "rating": null,
      "review_count": null,
      "in_stock": true,
      "is_on_sale": false,
      "scraped_at": "2025-08-06T03:09:00.428Z",
      "page_number": 32,
      "source_url": "https://www.coles.com.au/browse/dairy-eggs-fridge?page=32",
      "is_sponsored": null
    },
    {
      "title": "Australia's Own Cholesterol Lowering Milk | 1L",
      "current_price": 2.8,
      "original_price": null,
      "discount_percentage": null,
      "discount_amount": null,
      "image_url": "https://www.coles.com.au/_next/image?url=https%3A%2F%2Fcdn.productimages.coles.com.au%2Fproductimages%2F6%2F6506589.jpg&w=640&q=90",
      "product_url": "https://www.coles.com.au/product/australia's-own-cholesterol-lowering-milk-1l-6506589",
      "category": "dairy-eggs-fridge",
      "brand": null,
      "weight_size": null,
      "per_unit_price": "$2.80 per 1L",
      "rating": null,
      "review_count": null,
      "in_stock": true,
      "is_on_sale": false,
      "scraped_at": "2025-08-06T03:09:00.428Z",
      "page_number": 32,
      "source_url": "https://www.coles.com.au/browse/dairy-eggs-fridge?page=32",
      "is_sponsored": null
    },
    {
      "title": "Procal Authentic Greek Yoghurt | 900g",
      "current_price": 7,
      "original_price": null,
      "discount_percentage": null,
      "discount_amount": null,
      "image_url": "https://www.coles.com.au/_next/image?url=https%3A%2F%2Fcdn.productimages.coles.com.au%2Fproductimages%2F6%2F6523216.jpg&w=640&q=90",
      "product_url": "https://www.coles.com.au/product/procal-authentic-greek-yoghurt-900g-6523216",
      "category": "dairy-eggs-fridge",
      "brand": null,
      "weight_size": null,
      "per_unit_price": "$0.78 per 100g",
      "rating": null,
      "review_count": null,
      "in_stock": true,
      "is_on_sale": false,
      "scraped_at": "2025-08-06T03:09:00.428Z",
      "page_number": 32,
      "source_url": "https://www.coles.com.au/browse/dairy-eggs-fridge?page=32",
      "is_sponsored": null
    },
    {
      "title": "Coles Finest French Truffle Brie | approx. 100g",
      "current_price": 6.8,
      "original_price": null,
      "discount_percentage": null,
      "discount_amount": null,
      "image_url": "https://www.coles.com.au/_next/image?url=https%3A%2F%2Fcdn.productimages.coles.com.au%2Fproductimages%2F6%2F6525030.jpg&w=640&q=90",
      "product_url": "https://www.coles.com.au/product/coles-finest-french-truffle-brie-approx.-100g-6525030",
      "category": "dairy-eggs-fridge",
      "brand": null,
      "weight_size": null,
      "per_unit_price": "$68.00 per 1kg",
      "rating": null,
      "review_count": null,
      "in_stock": true,
      "is_on_sale": false,
      "scraped_at": "2025-08-06T03:09:00.428Z",
      "page_number": 32,
      "source_url": "https://www.coles.com.au/browse/dairy-eggs-fridge?page=32",
      "is_sponsored": null
    },
    {
      "title": "Coles Avocado Dip | 200g",
      "current_price": 2.6,
      "original_price": null,
      "discount_percentage": null,
      "discount_amount": null,
      "image_url": "https://www.coles.com.au/_next/image?url=https%3A%2F%2Fcdn.productimages.coles.com.au%2Fproductimages%2F6%2F6530710.jpg&w=640&q=90",
      "product_url": "https://www.coles.com.au/product/coles-avocado-dip-200g-6530710",
      "category": "dairy-eggs-fridge",
      "brand": null,
      "weight_size": null,
      "per_unit_price": "$1.30 per 100g",
      "rating": null,
      "review_count": null,
      "in_stock": true,
      "is_on_sale": false,
      "scraped_at": "2025-08-06T03:09:00.428Z",
      "page_number": 32,
      "source_url": "https://www.coles.com.au/browse/dairy-eggs-fridge?page=32",
      "is_sponsored": null
    },
    {
      "title": "Coles Hommus Dip | 200g",
      "current_price": 2.6,
      "original_price": null,
      "discount_percentage": null,
      "discount_amount": null,
      "image_url": "https://www.coles.com.au/_next/image?url=https%3A%2F%2Fcdn.productimages.coles.com.au%2Fproductimages%2F6%2F6530721.jpg&w=640&q=90",
      "product_url": "https://www.coles.com.au/product/coles-hommus-dip-200g-6530721",
      "category": "dairy-eggs-fridge",
      "brand": null,
      "weight_size": null,
      "per_unit_price": "$1.30 per 100g",
      "rating": null,
      "review_count": null,
      "in_stock": true,
      "is_on_sale": false,
      "scraped_at": "2025-08-06T03:09:00.428Z",
      "page_number": 32,
      "source_url": "https://www.coles.com.au/browse/dairy-eggs-fridge?page=32",
      "is_sponsored": null
    },
    {
      "title": "Coles French Onion Dip | 200g",
      "current_price": 2.6,
      "original_price": null,
      "discount_percentage": null,
      "discount_amount": null,
      "image_url": "https://www.coles.com.au/_next/image?url=https%3A%2F%2Fcdn.productimages.coles.com.au%2Fproductimages%2F6%2F6530743.jpg&w=640&q=90",
      "product_url": "https://www.coles.com.au/product/coles-french-onion-dip-200g-6530743",
      "category": "dairy-eggs-fridge",
      "brand": null,
      "weight_size": null,
      "per_unit_price": "$1.30 per 100g",
      "rating": null,
      "review_count": null,
      "in_stock": true,
      "is_on_sale": false,
      "scraped_at": "2025-08-06T03:09:00.428Z",
      "page_number": 32,
      "source_url": "https://www.coles.com.au/browse/dairy-eggs-fridge?page=32",
      "is_sponsored": null
    },
    {
      "title": "Mersey Valley Club Original Cheddar Cheese | 235g",
      "current_price": 9.9,
      "original_price": null,
      "discount_percentage": null,
      "discount_amount": null,
      "image_url": "https://www.coles.com.au/_next/image?url=https%3A%2F%2Fcdn.productimages.coles.com.au%2Fproductimages%2F6%2F6533005.jpg&w=640&q=90",
      "product_url": "https://www.coles.com.au/product/mersey-valley-club-original-cheddar-cheese-235g-6533005",
      "category": "dairy-eggs-fridge",
      "brand": null,
      "weight_size": null,
      "per_unit_price": "$42.13 per 1kg",
      "rating": null,
      "review_count": null,
      "in_stock": true,
      "is_on_sale": false,
      "scraped_at": "2025-08-06T03:09:00.428Z",
      "page_number": 32,
      "source_url": "https://www.coles.com.au/browse/dairy-eggs-fridge?page=32",
      "is_sponsored": null
    },
    {
      "title": "Mersey Valley Club Pickled Onion Cheddar Cheese | 235g",
      "current_price": 9.9,
      "original_price": null,
      "discount_percentage": null,
      "discount_amount": null,
      "image_url": "https://www.coles.com.au/_next/image?url=https%3A%2F%2Fcdn.productimages.coles.com.au%2Fproductimages%2F6%2F6533060.jpg&w=640&q=90",
      "product_url": "https://www.coles.com.au/product/mersey-valley-club-pickled-onion-cheddar-cheese-235g-6533060",
      "category": "dairy-eggs-fridge",
      "brand": null,
      "weight_size": null,
      "per_unit_price": "$42.13 per 1kg",
      "rating": null,
      "review_count": null,
      "in_stock": true,
      "is_on_sale": false,
      "scraped_at": "2025-08-06T03:09:00.428Z",
      "page_number": 32,
      "source_url": "https://www.coles.com.au/browse/dairy-eggs-fridge?page=32",
      "is_sponsored": null
    },
    {
      "title": "Gippsland Dairy Smooth & Creamy Twist Yoghurt | 700g",
      "current_price": 7.9,
      "original_price": null,
      "discount_percentage": null,
      "discount_amount": null,
      "image_url": "https://www.coles.com.au/_next/image?url=https%3A%2F%2Fcdn.productimages.coles.com.au%2Fproductimages%2F6%2F6560008.jpg&w=640&q=90",
      "product_url": "https://www.coles.com.au/product/gippsland-dairy-smooth-and-creamy-twist-yoghurt-700g-6560008",
      "category": "dairy-eggs-fridge",
      "brand": null,
      "weight_size": null,
      "per_unit_price": "$1.13 per 100g",
      "rating": null,
      "review_count": null,
      "in_stock": true,
      "is_on_sale": false,
      "scraped_at": "2025-08-06T03:09:00.428Z",
      "page_number": 32,
      "source_url": "https://www.coles.com.au/browse/dairy-eggs-fridge?page=32",
      "is_sponsored": null
    },
    {
      "title": "Farmers Union Light Greek Style Natural Yoghurt | 1kg",
      "current_price": 6.5,
      "original_price": null,
      "discount_percentage": null,
      "discount_amount": null,
      "image_url": "https://www.coles.com.au/_next/image?url=https%3A%2F%2Fcdn.productimages.coles.com.au%2Fproductimages%2F6%2F6567776.jpg&w=640&q=90",
      "product_url": "https://www.coles.com.au/product/farmers-union-light-greek-style-natural-yoghurt-1kg-6567776",
      "category": "dairy-eggs-fridge",
      "brand": null,
      "weight_size": null,
      "per_unit_price": "$0.65 per 100g",
      "rating": null,
      "review_count": null,
      "in_stock": true,
      "is_on_sale": false,
      "scraped_at": "2025-08-06T03:09:00.428Z",
      "page_number": 32,
      "source_url": "https://www.coles.com.au/browse/dairy-eggs-fridge?page=32",
      "is_sponsored": null
    },
    {
      "title": "Bega Dairy Tasty Grated Cheese | 500g",
      "current_price": 10.5,
      "original_price": null,
      "discount_percentage": null,
      "discount_amount": null,
      "image_url": "https://www.coles.com.au/_next/image?url=https%3A%2F%2Fcdn.productimages.coles.com.au%2Fproductimages%2F6%2F6576347.jpg&w=640&q=90",
      "product_url": "https://www.coles.com.au/product/bega-dairy-tasty-grated-cheese-500g-6576347",
      "category": "dairy-eggs-fridge",
      "brand": null,
      "weight_size": null,
      "per_unit_price": "$21.00 per 1kg",
      "rating": null,
      "review_count": null,
      "in_stock": true,
      "is_on_sale": false,
      "scraped_at": "2025-08-06T03:09:00.428Z",
      "page_number": 32,
      "source_url": "https://www.coles.com.au/browse/dairy-eggs-fridge?page=32",
      "is_sponsored": null
    },
    {
      "title": "Mainland Cheese Slices Extra Tasty | 210g",
      "current_price": 6,
      "original_price": null,
      "discount_percentage": null,
      "discount_amount": null,
      "image_url": "https://www.coles.com.au/_next/image?url=https%3A%2F%2Fcdn.productimages.coles.com.au%2Fproductimages%2F6%2F6576788.jpg&w=640&q=90",
      "product_url": "https://www.coles.com.au/product/mainland-cheese-slices-extra-tasty-210g-6576788",
      "category": "dairy-eggs-fridge",
      "brand": null,
      "weight_size": null,
      "per_unit_price": "$28.57 per 1kgWas $7.00 on Jul 2025",
      "rating": null,
      "review_count": null,
      "in_stock": true,
      "is_on_sale": false,
      "scraped_at": "2025-08-06T03:09:00.428Z",
      "page_number": 32,
      "source_url": "https://www.coles.com.au/browse/dairy-eggs-fridge?page=32",
      "is_sponsored": null
    },
    {
      "title": "Perfect Italiano Cheese Extra Sharp Grated Parmesan | 125g",
      "current_price": 4,
      "original_price": null,
      "discount_percentage": null,
      "discount_amount": null,
      "image_url": "https://www.coles.com.au/_next/image?url=https%3A%2F%2Fcdn.productimages.coles.com.au%2Fproductimages%2F6%2F6577000.jpg&w=640&q=90",
      "product_url": "https://www.coles.com.au/product/perfect-italiano-cheese-extra-sharp-grated-parmesan-125g-6577000",
      "category": "dairy-eggs-fridge",
      "brand": null,
      "weight_size": null,
      "per_unit_price": "$32.00 per 1kgWas $4.50 on May 2025",
      "rating": null,
      "review_count": null,
      "in_stock": true,
      "is_on_sale": false,
      "scraped_at": "2025-08-06T03:09:00.428Z",
      "page_number": 32,
      "source_url": "https://www.coles.com.au/browse/dairy-eggs-fridge?page=32",
      "is_sponsored": null
    },
    {
      "title": "Tasmanian Heritage Trilogy Summer Herbs Vintage Cheddar & Sundried  ... 140g",
      "current_price": 6.5,
      "original_price": null,
      "discount_percentage": null,
      "discount_amount": null,
      "image_url": "https://www.coles.com.au/_next/image?url=https%3A%2F%2Fcdn.productimages.coles.com.au%2Fproductimages%2F6%2F6578069.jpg&w=640&q=90",
      "product_url": "https://www.coles.com.au/product/tasmanian-heritage-trilogy-summer-herbs-vintage-cheddar-and-sundried-tomato-140g-6578069",
      "category": "dairy-eggs-fridge",
      "brand": null,
      "weight_size": null,
      "per_unit_price": "$46.43 per 1kg",
      "rating": null,
      "review_count": null,
      "in_stock": true,
      "is_on_sale": false,
      "scraped_at": "2025-08-06T03:09:00.428Z",
      "page_number": 32,
      "source_url": "https://www.coles.com.au/browse/dairy-eggs-fridge?page=32",
      "is_sponsored": null
    },
    {
      "title": "South Cape Apricot & Almond Cream Cheese | 200g",
      "current_price": 5.9,
      "original_price": null,
      "discount_percentage": null,
      "discount_amount": null,
      "image_url": "https://www.coles.com.au/_next/image?url=https%3A%2F%2Fcdn.productimages.coles.com.au%2Fproductimages%2F6%2F6581201.jpg&w=640&q=90",
      "product_url": "https://www.coles.com.au/product/south-cape-apricot-and-almond-cream-cheese-200g-6581201",
      "category": "dairy-eggs-fridge",
      "brand": null,
      "weight_size": null,
      "per_unit_price": "$29.50 per 1kgWas $6.50 on Jul 2025",
      "rating": null,
      "review_count": null,
      "in_stock": true,
      "is_on_sale": false,
      "scraped_at": "2025-08-06T03:09:00.428Z",
      "page_number": 32,
      "source_url": "https://www.coles.com.au/browse/dairy-eggs-fridge?page=32",
      "is_sponsored": null
    },
    {
      "title": "South Cape Spring Onion & Chive Cream Cheese | 200g",
      "current_price": 5.9,
      "original_price": null,
      "discount_percentage": null,
      "discount_amount": null,
      "image_url": "https://www.coles.com.au/_next/image?url=https%3A%2F%2Fcdn.productimages.coles.com.au%2Fproductimages%2F6%2F6581256.jpg&w=640&q=90",
      "product_url": "https://www.coles.com.au/product/south-cape-spring-onion-and-chive-cream-cheese-200g-6581256",
      "category": "dairy-eggs-fridge",
      "brand": null,
      "weight_size": null,
      "per_unit_price": "$29.50 per 1kgWas $6.50 on Jul 2025",
      "rating": null,
      "review_count": null,
      "in_stock": true,
      "is_on_sale": false,
      "scraped_at": "2025-08-06T03:09:00.428Z",
      "page_number": 32,
      "source_url": "https://www.coles.com.au/browse/dairy-eggs-fridge?page=32",
      "is_sponsored": null
    },
    {
      "title": "Meggles Free Range Eggs Xlarge 12 Pack | 700g",
      "current_price": 8.8,
      "original_price": null,
      "discount_percentage": null,
      "discount_amount": null,
      "image_url": "https://www.coles.com.au/_next/image?url=https%3A%2F%2Fcdn.productimages.coles.com.au%2Fproductimages%2F6%2F6594622.jpg&w=640&q=90",
      "product_url": "https://www.coles.com.au/product/meggles-free-range-eggs-xlarge-12-pack-700g-6594622",
      "category": "dairy-eggs-fridge",
      "brand": null,
      "weight_size": null,
      "per_unit_price": "$1.26 per 100g",
      "rating": null,
      "review_count": null,
      "in_stock": true,
      "is_on_sale": false,
      "scraped_at": "2025-08-06T03:09:00.428Z",
      "page_number": 32,
      "source_url": "https://www.coles.com.au/browse/dairy-eggs-fridge?page=32",
      "is_sponsored": null
    },
    {
      "title": "Farmers Union No Added Sugar Kids Yogurt Pouch Vanilla | 130g",
      "current_price": 2.2,
      "original_price": null,
      "discount_percentage": null,
      "discount_amount": null,
      "image_url": "https://www.coles.com.au/_next/image?url=https%3A%2F%2Fcdn.productimages.coles.com.au%2Fproductimages%2F6%2F6600678.jpg&w=640&q=90",
      "product_url": "https://www.coles.com.au/product/farmers-union-no-added-sugar-kids-yogurt-pouch-vanilla-130g-6600678",
      "category": "dairy-eggs-fridge",
      "brand": null,
      "weight_size": null,
      "per_unit_price": "$1.69 per 100g",
      "rating": null,
      "review_count": null,
      "in_stock": true,
      "is_on_sale": false,
      "scraped_at": "2025-08-06T03:09:00.428Z",
      "page_number": 32,
      "source_url": "https://www.coles.com.au/browse/dairy-eggs-fridge?page=32",
      "is_sponsored": null
    },
    {
      "title": "Farmers Union No Added Sugar Kids Yogurt Pouch Strawberry | 130g",
      "current_price": 2.2,
      "original_price": null,
      "discount_percentage": null,
      "discount_amount": null,
      "image_url": "https://www.coles.com.au/_next/image?url=https%3A%2F%2Fcdn.productimages.coles.com.au%2Fproductimages%2F6%2F6600689.jpg&w=640&q=90",
      "product_url": "https://www.coles.com.au/product/farmers-union-no-added-sugar-kids-yogurt-pouch-strawberry-130g-6600689",
      "category": "dairy-eggs-fridge",
      "brand": null,
      "weight_size": null,
      "per_unit_price": "$1.69 per 100g",
      "rating": null,
      "review_count": null,
      "in_stock": true,
      "is_on_sale": false,
      "scraped_at": "2025-08-06T03:09:00.428Z",
      "page_number": 32,
      "source_url": "https://www.coles.com.au/browse/dairy-eggs-fridge?page=32",
      "is_sponsored": null
    },
    {
      "title": "Farmers Union No Added Sugar Kids Yogurt Pouch Blueberry | 130g",
      "current_price": 2.2,
      "original_price": null,
      "discount_percentage": null,
      "discount_amount": null,
      "image_url": "https://www.coles.com.au/_next/image?url=https%3A%2F%2Fcdn.productimages.coles.com.au%2Fproductimages%2F6%2F6600805.jpg&w=640&q=90",
      "product_url": "https://www.coles.com.au/product/farmers-union-no-added-sugar-kids-yogurt-pouch-blueberry-130g-6600805",
      "category": "dairy-eggs-fridge",
      "brand": null,
      "weight_size": null,
      "per_unit_price": "$1.69 per 100g",
      "rating": null,
      "review_count": null,
      "in_stock": true,
      "is_on_sale": false,
      "scraped_at": "2025-08-06T03:09:00.428Z",
      "page_number": 32,
      "source_url": "https://www.coles.com.au/browse/dairy-eggs-fridge?page=32",
      "is_sponsored": null
    },
    {
      "title": "Farmers Union No Added Sugar Kids Yogurt Pouch Tropical | 130g",
      "current_price": 2.2,
      "original_price": null,
      "discount_percentage": null,
      "discount_amount": null,
      "image_url": "https://www.coles.com.au/_next/image?url=https%3A%2F%2Fcdn.productimages.coles.com.au%2Fproductimages%2F6%2F6601309.jpg&w=640&q=90",
      "product_url": "https://www.coles.com.au/product/farmers-union-no-added-sugar-kids-yogurt-pouch-tropical-130g-6601309",
      "category": "dairy-eggs-fridge",
      "brand": null,
      "weight_size": null,
      "per_unit_price": "$1.69 per 100g",
      "rating": null,
      "review_count": null,
      "in_stock": true,
      "is_on_sale": false,
      "scraped_at": "2025-08-06T03:09:00.428Z",
      "page_number": 32,
      "source_url": "https://www.coles.com.au/browse/dairy-eggs-fridge?page=32",
      "is_sponsored": null
    },
    {
      "title": "Farmers Union No Added Sugar Kids Yogurt Pouch Banana | 130g",
      "current_price": 2.2,
      "original_price": null,
      "discount_percentage": null,
      "discount_amount": null,
      "image_url": "https://www.coles.com.au/_next/image?url=https%3A%2F%2Fcdn.productimages.coles.com.au%2Fproductimages%2F6%2F6601310.jpg&w=640&q=90",
      "product_url": "https://www.coles.com.au/product/farmers-union-no-added-sugar-kids-yogurt-pouch-banana-130g-6601310",
      "category": "dairy-eggs-fridge",
      "brand": null,
      "weight_size": null,
      "per_unit_price": "$1.69 per 100g",
      "rating": null,
      "review_count": null,
      "in_stock": true,
      "is_on_sale": false,
      "scraped_at": "2025-08-06T03:09:00.428Z",
      "page_number": 32,
      "source_url": "https://www.coles.com.au/browse/dairy-eggs-fridge?page=32",
      "is_sponsored": null
    },
    {
      "title": "Dairy Farmers Thick & Creamy Yoghurt Mango & Finger Lime | 550g",
      "current_price": 5.5,
      "original_price": null,
      "discount_percentage": null,
      "discount_amount": null,
      "image_url": "https://www.coles.com.au/_next/image?url=https%3A%2F%2Fcdn.productimages.coles.com.au%2Fproductimages%2F6%2F6604250.jpg&w=640&q=90",
      "product_url": "https://www.coles.com.au/product/dairy-farmers-thick-and-creamy-yoghurt-mango-and-finger-lime-550g-6604250",
      "category": "dairy-eggs-fridge",
      "brand": null,
      "weight_size": null,
      "per_unit_price": "$1.00 per 100g",
      "rating": null,
      "review_count": null,
      "in_stock": true,
      "is_on_sale": false,
      "scraped_at": "2025-08-06T03:09:00.428Z",
      "page_number": 32,
      "source_url": "https://www.coles.com.au/browse/dairy-eggs-fridge?page=32",
      "is_sponsored": null
    },
    {
      "title": "Farmers Union Greek Style Natural Yogurt | 240g",
      "current_price": 3.1,
      "original_price": null,
      "discount_percentage": null,
      "discount_amount": null,
      "image_url": "https://www.coles.com.au/_next/image?url=https%3A%2F%2Fcdn.productimages.coles.com.au%2Fproductimages%2F6%2F6604351.jpg&w=640&q=90",
      "product_url": "https://www.coles.com.au/product/farmers-union-greek-style-natural-yogurt-240g-6604351",
      "category": "dairy-eggs-fridge",
      "brand": null,
      "weight_size": null,
      "per_unit_price": "$1.29 per 100g",
      "rating": null,
      "review_count": null,
      "in_stock": true,
      "is_on_sale": false,
      "scraped_at": "2025-08-06T03:09:00.428Z",
      "page_number": 32,
      "source_url": "https://www.coles.com.au/browse/dairy-eggs-fridge?page=32",
      "is_sponsored": null
    },
    {
      "title": "Bulla Dollop Cream | 200mL",
      "current_price": 3.8,
      "original_price": null,
      "discount_percentage": null,
      "discount_amount": null,
      "image_url": "https://www.coles.com.au/_next/image?url=https%3A%2F%2Fcdn.productimages.coles.com.au%2Fproductimages%2F6%2F6608148.jpg&w=640&q=90",
      "product_url": "https://www.coles.com.au/product/bulla-dollop-cream-200ml-6608148",
      "category": "dairy-eggs-fridge",
      "brand": null,
      "weight_size": null,
      "per_unit_price": "$1.90 per 100mL",
      "rating": null,
      "review_count": null,
      "in_stock": true,
      "is_on_sale": false,
      "scraped_at": "2025-08-06T03:09:00.428Z",
      "page_number": 32,
      "source_url": "https://www.coles.com.au/browse/dairy-eggs-fridge?page=32",
      "is_sponsored": null
    },
    {
      "title": "Yoplait Yoghurt Mixed Berry | 1kg",
      "current_price": 4.75,
      "original_price": null,
      "discount_percentage": null,
      "discount_amount": null,
      "image_url": "https://www.coles.com.au/_next/image?url=https%3A%2F%2Fcdn.productimages.coles.com.au%2Fproductimages%2F6%2F6613691.jpg&w=640&q=90",
      "product_url": "https://www.coles.com.au/product/yoplait-yoghurt-mixed-berry-1kg-6613691",
      "category": "dairy-eggs-fridge",
      "brand": null,
      "weight_size": null,
      "per_unit_price": "$0.48 per 100g",
      "rating": null,
      "review_count": null,
      "in_stock": true,
      "is_on_sale": false,
      "scraped_at": "2025-08-06T03:09:00.428Z",
      "page_number": 32,
      "source_url": "https://www.coles.com.au/browse/dairy-eggs-fridge?page=32",
      "is_sponsored": null
    }
  ],
  "summary": {
    "total_products": 58,
    "products_on_sale": 0,
    "products_with_ratings": 0,
    "average_price": 5.425000000000001,
    "price_range": {
      "min": 2,
      "max": 11
    }
  }
}