{
  "extraction_info": {
    "timestamp": "2025-08-06T03:15:08.546Z",
    "page_url": "https://www.coles.com.au/browse/chips-chocolates-snacks?page=7",
    "category": "chips-chocolates-snacks",
    "page_number": 7,
    "selector_set_used": "high_confidence",
    "total_products": 58,
    "total_elements_found": 58
  },
  "products": [
    {
      "title": "Cadbury Dairy Milk Caramello Chocolate Bites | 142g",
      "current_price": 7,
      "original_price": null,
      "discount_percentage": null,
      "discount_amount": null,
      "image_url": "https://www.coles.com.au/_next/image?url=https%3A%2F%2Fcdn.productimages.coles.com.au%2Fproductimages%2F5%2F5889471.jpg&w=640&q=90",
      "product_url": "https://www.coles.com.au/product/cadbury-dairy-milk-caramello-chocolate-bites-142g-5889471",
      "category": "chips-chocolates-snacks",
      "brand": null,
      "weight_size": null,
      "per_unit_price": "$4.93 per 100g",
      "rating": 0,
      "review_count": 0,
      "in_stock": true,
      "is_on_sale": false,
      "scraped_at": "2025-08-06T03:15:08.545Z",
      "page_number": 7,
      "source_url": "https://www.coles.com.au/browse/chips-chocolates-snacks?page=7",
      "is_sponsored": null
    },
    {
      "title": "Oreo Double Stuff Cookies | 131g",
      "current_price": 3,
      "original_price": null,
      "discount_percentage": null,
      "discount_amount": null,
      "image_url": "https://www.coles.com.au/_next/image?url=https%3A%2F%2Fcdn.productimages.coles.com.au%2Fproductimages%2F3%2F3763122.jpg&w=640&q=90",
      "product_url": "https://www.coles.com.au/product/oreo-double-stuff-cookies-131g-3763122",
      "category": "chips-chocolates-snacks",
      "brand": null,
      "weight_size": null,
      "per_unit_price": "$2.29 per 100g",
      "rating": 0,
      "review_count": 0,
      "in_stock": true,
      "is_on_sale": false,
      "scraped_at": "2025-08-06T03:15:08.545Z",
      "page_number": 7,
      "source_url": "https://www.coles.com.au/browse/chips-chocolates-snacks?page=7",
      "is_sponsored": true
    },
    {
      "title": "Uncle Tobys Le Snak Tasty Cheese Dip & Crackers School Lunchbox Sn ... 132g",
      "current_price": 4,
      "original_price": null,
      "discount_percentage": null,
      "discount_amount": null,
      "image_url": "https://www.coles.com.au/_next/image?url=https%3A%2F%2Fcdn.productimages.coles.com.au%2Fproductimages%2F4%2F4954750.jpg&w=640&q=90",
      "product_url": "https://www.coles.com.au/product/uncle-tobys-le-snak-tasty-cheese-dip-and-crackers-school-lunchbox-snacks-132g-4954750",
      "category": "chips-chocolates-snacks",
      "brand": null,
      "weight_size": null,
      "per_unit_price": "$3.03 per 100g | Was $5.50",
      "rating": 0,
      "review_count": 0,
      "in_stock": true,
      "is_on_sale": false,
      "scraped_at": "2025-08-06T03:15:08.545Z",
      "page_number": 7,
      "source_url": "https://www.coles.com.au/browse/chips-chocolates-snacks?page=7",
      "is_sponsored": true
    },
    {
      "title": "Uncle Tobys Rainbow Berry Berry Roll Ups School Lunchbox Snacks | 94g",
      "current_price": 4,
      "original_price": null,
      "discount_percentage": null,
      "discount_amount": null,
      "image_url": "https://www.coles.com.au/_next/image?url=https%3A%2F%2Fcdn.productimages.coles.com.au%2Fproductimages%2F6%2F6899164.jpg&w=640&q=90",
      "product_url": "https://www.coles.com.au/product/uncle-tobys-rainbow-berry-berry-roll-ups-school-lunchbox-snacks-94g-6899164",
      "category": "chips-chocolates-snacks",
      "brand": null,
      "weight_size": null,
      "per_unit_price": "$4.26 per 100g | Was $5.50",
      "rating": 3.9,
      "review_count": 8,
      "in_stock": true,
      "is_on_sale": false,
      "scraped_at": "2025-08-06T03:15:08.545Z",
      "page_number": 7,
      "source_url": "https://www.coles.com.au/browse/chips-chocolates-snacks?page=7",
      "is_sponsored": true
    },
    {
      "title": "Smiths Snack Mix Variety Multipack 20 Pack | 395g",
      "current_price": 8.9,
      "original_price": null,
      "discount_percentage": null,
      "discount_amount": null,
      "image_url": "https://www.coles.com.au/_next/image?url=https%3A%2F%2Fcdn.productimages.coles.com.au%2Fproductimages%2F3%2F3706060.jpg&w=640&q=90",
      "product_url": "https://www.coles.com.au/product/smiths-snack-mix-variety-multipack-20-pack-395g-3706060",
      "category": "chips-chocolates-snacks",
      "brand": null,
      "weight_size": null,
      "per_unit_price": "$2.25 per 100g",
      "rating": 4.7,
      "review_count": 332,
      "in_stock": true,
      "is_on_sale": false,
      "scraped_at": "2025-08-06T03:15:08.545Z",
      "page_number": 7,
      "source_url": "https://www.coles.com.au/browse/chips-chocolates-snacks?page=7",
      "is_sponsored": true
    },
    {
      "title": "Thins Top 20 Variety Chips Multipack Lunch Box Snacks 20 Pack | 375g",
      "current_price": 7.5,
      "original_price": null,
      "discount_percentage": null,
      "discount_amount": null,
      "image_url": "https://www.coles.com.au/_next/image?url=https%3A%2F%2Fcdn.productimages.coles.com.au%2Fproductimages%2F4%2F4843850.jpg&w=640&q=90",
      "product_url": "https://www.coles.com.au/product/thins-top-20-variety-chips-multipack-lunch-box-snacks-20-pack-375g-4843850",
      "category": "chips-chocolates-snacks",
      "brand": null,
      "weight_size": null,
      "per_unit_price": "$2.00 per 100g",
      "rating": 0,
      "review_count": 0,
      "in_stock": true,
      "is_on_sale": false,
      "scraped_at": "2025-08-06T03:15:08.545Z",
      "page_number": 7,
      "source_url": "https://www.coles.com.au/browse/chips-chocolates-snacks?page=7",
      "is_sponsored": true
    },
    {
      "title": "Uncle Tobys Chewy Choc Chip Muesli Bars School Lunchbox Snacks | 185g",
      "current_price": 4,
      "original_price": null,
      "discount_percentage": null,
      "discount_amount": null,
      "image_url": "https://www.coles.com.au/_next/image?url=https%3A%2F%2Fcdn.productimages.coles.com.au%2Fproductimages%2F4%2F4975192.jpg&w=640&q=90",
      "product_url": "https://www.coles.com.au/product/uncle-tobys-chewy-choc-chip-muesli-bars-school-lunchbox-snacks-185g-4975192",
      "category": "chips-chocolates-snacks",
      "brand": null,
      "weight_size": null,
      "per_unit_price": "$2.16 per 100g | Was $5.50",
      "rating": 4.2,
      "review_count": 79,
      "in_stock": true,
      "is_on_sale": false,
      "scraped_at": "2025-08-06T03:15:08.545Z",
      "page_number": 7,
      "source_url": "https://www.coles.com.au/browse/chips-chocolates-snacks?page=7",
      "is_sponsored": true
    },
    {
      "title": "Sunbites Snack Crackers Mix 2 Multipack 12 Pack | 288g",
      "current_price": 5.5,
      "original_price": null,
      "discount_percentage": null,
      "discount_amount": null,
      "image_url": "https://www.coles.com.au/_next/image?url=https%3A%2F%2Fcdn.productimages.coles.com.au%2Fproductimages%2F7%2F7483558.jpg&w=640&q=90",
      "product_url": "https://www.coles.com.au/product/sunbites-snack-crackers-mix-2-multipack-12-pack-288g-7483558",
      "category": "chips-chocolates-snacks",
      "brand": null,
      "weight_size": null,
      "per_unit_price": "$1.91 per 100g",
      "rating": 4.7,
      "review_count": 56,
      "in_stock": true,
      "is_on_sale": false,
      "scraped_at": "2025-08-06T03:15:08.545Z",
      "page_number": 7,
      "source_url": "https://www.coles.com.au/browse/chips-chocolates-snacks?page=7",
      "is_sponsored": true
    },
    {
      "title": "Cadbury Dairy Milk Marvellous Creations Jelly Popping Candy Cho ... 190g",
      "current_price": 8,
      "original_price": null,
      "discount_percentage": null,
      "discount_amount": null,
      "image_url": "https://www.coles.com.au/_next/image?url=https%3A%2F%2Fcdn.productimages.coles.com.au%2Fproductimages%2F2%2F2898997.jpg&w=640&q=90",
      "product_url": "https://www.coles.com.au/product/cadbury-dairy-milk-marvellous-creations-jelly-popping-candy-chocolate-block-190g-2898997",
      "category": "chips-chocolates-snacks",
      "brand": null,
      "weight_size": null,
      "per_unit_price": "$4.21 per 100g",
      "rating": 0,
      "review_count": 0,
      "in_stock": true,
      "is_on_sale": false,
      "scraped_at": "2025-08-06T03:15:08.545Z",
      "page_number": 7,
      "source_url": "https://www.coles.com.au/browse/chips-chocolates-snacks?page=7",
      "is_sponsored": true
    },
    {
      "title": "Smiths Potato Chips Crinkle Flavour Mix Variety 20 Pack | 380g",
      "current_price": 8.9,
      "original_price": null,
      "discount_percentage": null,
      "discount_amount": null,
      "image_url": "https://www.coles.com.au/_next/image?url=https%3A%2F%2Fcdn.productimages.coles.com.au%2Fproductimages%2F4%2F4826829.jpg&w=640&q=90",
      "product_url": "https://www.coles.com.au/product/smiths-potato-chips-crinkle-flavour-mix-variety-20-pack-380g-4826829",
      "category": "chips-chocolates-snacks",
      "brand": null,
      "weight_size": null,
      "per_unit_price": "$2.34 per 100g",
      "rating": 4.6,
      "review_count": 281,
      "in_stock": true,
      "is_on_sale": false,
      "scraped_at": "2025-08-06T03:15:08.545Z",
      "page_number": 7,
      "source_url": "https://www.coles.com.au/browse/chips-chocolates-snacks?page=7",
      "is_sponsored": true
    },
    {
      "title": "Uncle Tobys Chokito Mueli Bars | 145g",
      "current_price": 4,
      "original_price": null,
      "discount_percentage": null,
      "discount_amount": null,
      "image_url": "https://www.coles.com.au/_next/image?url=https%3A%2F%2Fcdn.productimages.coles.com.au%2Fproductimages%2F9%2F9068127.jpg&w=640&q=90",
      "product_url": "https://www.coles.com.au/product/uncle-tobys-chokito-mueli-bars-145g-9068127",
      "category": "chips-chocolates-snacks",
      "brand": null,
      "weight_size": null,
      "per_unit_price": "$2.76 per 100g | Was $5.50",
      "rating": 4.2,
      "review_count": 80,
      "in_stock": true,
      "is_on_sale": false,
      "scraped_at": "2025-08-06T03:15:08.545Z",
      "page_number": 7,
      "source_url": "https://www.coles.com.au/browse/chips-chocolates-snacks?page=7",
      "is_sponsored": true
    },
    {
      "title": "Cadbury Dairy Milk Slices Crackle Chocolate Block | 165g",
      "current_price": 8,
      "original_price": null,
      "discount_percentage": null,
      "discount_amount": null,
      "image_url": "https://www.coles.com.au/_next/image?url=https%3A%2F%2Fcdn.productimages.coles.com.au%2Fproductimages%2F6%2F6313111.jpg&w=640&q=90",
      "product_url": "https://www.coles.com.au/product/cadbury-dairy-milk-slices-crackle-chocolate-block-165g-6313111",
      "category": "chips-chocolates-snacks",
      "brand": null,
      "weight_size": null,
      "per_unit_price": "$4.85 per 100g",
      "rating": 4.3,
      "review_count": 93,
      "in_stock": true,
      "is_on_sale": false,
      "scraped_at": "2025-08-06T03:15:08.545Z",
      "page_number": 7,
      "source_url": "https://www.coles.com.au/browse/chips-chocolates-snacks?page=7",
      "is_sponsored": null
    },
    {
      "title": "Table Of Plenty Popped Rice Cakes Cheddar Cheese 6 Pack | 90g",
      "current_price": 6,
      "original_price": null,
      "discount_percentage": null,
      "discount_amount": null,
      "image_url": "https://www.coles.com.au/_next/image?url=https%3A%2F%2Fcdn.productimages.coles.com.au%2Fproductimages%2F7%2F7063075.jpg&w=640&q=90",
      "product_url": "https://www.coles.com.au/product/table-of-plenty-popped-rice-cakes-cheddar-cheese-6-pack-90g-7063075",
      "category": "chips-chocolates-snacks",
      "brand": null,
      "weight_size": null,
      "per_unit_price": "$6.67 per 100g",
      "rating": 0,
      "review_count": 0,
      "in_stock": true,
      "is_on_sale": false,
      "scraped_at": "2025-08-06T03:15:08.545Z",
      "page_number": 7,
      "source_url": "https://www.coles.com.au/browse/chips-chocolates-snacks?page=7",
      "is_sponsored": null
    },
    {
      "title": "Cadbury Dairy Milk Bubbly Mint Milk Chocolate Block | 160g",
      "current_price": 8,
      "original_price": null,
      "discount_percentage": null,
      "discount_amount": null,
      "image_url": "https://www.coles.com.au/_next/image?url=https%3A%2F%2Fcdn.productimages.coles.com.au%2Fproductimages%2F9%2F9901058.jpg&w=640&q=90",
      "product_url": "https://www.coles.com.au/product/cadbury-dairy-milk-bubbly-mint-milk-chocolate-block-160g-9901058",
      "category": "chips-chocolates-snacks",
      "brand": null,
      "weight_size": null,
      "per_unit_price": "$5.00 per 100g",
      "rating": 0,
      "review_count": 0,
      "in_stock": true,
      "is_on_sale": false,
      "scraped_at": "2025-08-06T03:15:08.545Z",
      "page_number": 7,
      "source_url": "https://www.coles.com.au/browse/chips-chocolates-snacks?page=7",
      "is_sponsored": null
    },
    {
      "title": "Arnott's Mini Choc Chip Cookies 7 Pack | 175g",
      "current_price": 5,
      "original_price": null,
      "discount_percentage": null,
      "discount_amount": null,
      "image_url": "https://www.coles.com.au/_next/image?url=https%3A%2F%2Fcdn.productimages.coles.com.au%2Fproductimages%2F2%2F2992157.jpg&w=640&q=90",
      "product_url": "https://www.coles.com.au/product/arnott's-mini-choc-chip-cookies-7-pack-175g-2992157",
      "category": "chips-chocolates-snacks",
      "brand": null,
      "weight_size": null,
      "per_unit_price": "$2.86 per 100g",
      "rating": 0,
      "review_count": 0,
      "in_stock": true,
      "is_on_sale": false,
      "scraped_at": "2025-08-06T03:15:08.545Z",
      "page_number": 7,
      "source_url": "https://www.coles.com.au/browse/chips-chocolates-snacks?page=7",
      "is_sponsored": null
    },
    {
      "title": "Cadbury Dairy Milk Pascall Clinkers Chocolate Block | 180g",
      "current_price": 8,
      "original_price": null,
      "discount_percentage": null,
      "discount_amount": null,
      "image_url": "https://www.coles.com.au/_next/image?url=https%3A%2F%2Fcdn.productimages.coles.com.au%2Fproductimages%2F4%2F4313609.jpg&w=640&q=90",
      "product_url": "https://www.coles.com.au/product/cadbury-dairy-milk-pascall-clinkers-chocolate-block-180g-4313609",
      "category": "chips-chocolates-snacks",
      "brand": null,
      "weight_size": null,
      "per_unit_price": "$4.71 per 100g",
      "rating": 0,
      "review_count": 0,
      "in_stock": true,
      "is_on_sale": false,
      "scraped_at": "2025-08-06T03:15:08.545Z",
      "page_number": 7,
      "source_url": "https://www.coles.com.au/browse/chips-chocolates-snacks?page=7",
      "is_sponsored": null
    },
    {
      "title": "Cadbury Dairy Milk Top Deck Chocolate Balls | 135g",
      "current_price": 7,
      "original_price": null,
      "discount_percentage": null,
      "discount_amount": null,
      "image_url": "https://www.coles.com.au/_next/image?url=https%3A%2F%2Fcdn.productimages.coles.com.au%2Fproductimages%2F5%2F5888592.jpg&w=640&q=90",
      "product_url": "https://www.coles.com.au/product/cadbury-dairy-milk-top-deck-chocolate-balls-135g-5888592",
      "category": "chips-chocolates-snacks",
      "brand": null,
      "weight_size": null,
      "per_unit_price": "$5.19 per 100g",
      "rating": 0,
      "review_count": 0,
      "in_stock": true,
      "is_on_sale": false,
      "scraped_at": "2025-08-06T03:15:08.545Z",
      "page_number": 7,
      "source_url": "https://www.coles.com.au/browse/chips-chocolates-snacks?page=7",
      "is_sponsored": null
    },
    {
      "title": "Coles Chocolate Fingers Biscuits | 200g",
      "current_price": 3,
      "original_price": null,
      "discount_percentage": null,
      "discount_amount": null,
      "image_url": "https://www.coles.com.au/_next/image?url=https%3A%2F%2Fcdn.productimages.coles.com.au%2Fproductimages%2F7%2F7378418.jpg&w=640&q=90",
      "product_url": "https://www.coles.com.au/product/coles-chocolate-fingers-biscuits-200g-7378418",
      "category": "chips-chocolates-snacks",
      "brand": null,
      "weight_size": null,
      "per_unit_price": "$1.50 per 100g",
      "rating": 0,
      "review_count": 0,
      "in_stock": true,
      "is_on_sale": false,
      "scraped_at": "2025-08-06T03:15:08.545Z",
      "page_number": 7,
      "source_url": "https://www.coles.com.au/browse/chips-chocolates-snacks?page=7",
      "is_sponsored": null
    },
    {
      "title": "Thins Onion Rings Sour Cream And Chives | 85g",
      "current_price": 5,
      "original_price": null,
      "discount_percentage": null,
      "discount_amount": null,
      "image_url": "https://www.coles.com.au/_next/image?url=https%3A%2F%2Fcdn.productimages.coles.com.au%2Fproductimages%2F7%2F7492446.jpg&w=640&q=90",
      "product_url": "https://www.coles.com.au/product/thins-onion-rings-sour-cream-and-chives-85g-7492446",
      "category": "chips-chocolates-snacks",
      "brand": null,
      "weight_size": null,
      "per_unit_price": "$5.88 per 100g",
      "rating": 0,
      "review_count": 0,
      "in_stock": true,
      "is_on_sale": false,
      "scraped_at": "2025-08-06T03:15:08.545Z",
      "page_number": 7,
      "source_url": "https://www.coles.com.au/browse/chips-chocolates-snacks?page=7",
      "is_sponsored": null
    },
    {
      "title": "Cadbury Dairy Milk Marvellous Creations Bites | 142g",
      "current_price": 7,
      "original_price": null,
      "discount_percentage": null,
      "discount_amount": null,
      "image_url": "https://www.coles.com.au/_next/image?url=https%3A%2F%2Fcdn.productimages.coles.com.au%2Fproductimages%2F9%2F9086388.jpg&w=640&q=90",
      "product_url": "https://www.coles.com.au/product/cadbury-dairy-milk-marvellous-creations-bites-142g-9086388",
      "category": "chips-chocolates-snacks",
      "brand": null,
      "weight_size": null,
      "per_unit_price": "$5.83 per 100g",
      "rating": 0,
      "review_count": 0,
      "in_stock": true,
      "is_on_sale": false,
      "scraped_at": "2025-08-06T03:15:08.545Z",
      "page_number": 7,
      "source_url": "https://www.coles.com.au/browse/chips-chocolates-snacks?page=7",
      "is_sponsored": null
    },
    {
      "title": "French Fries Potato Chips Multipack Lunch Box School Snacks Gluten Free  ... 111g",
      "current_price": 4.5,
      "original_price": null,
      "discount_percentage": null,
      "discount_amount": null,
      "image_url": "https://www.coles.com.au/_next/image?url=https%3A%2F%2Fcdn.productimages.coles.com.au%2Fproductimages%2F6%2F6290570.jpg&w=640&q=90",
      "product_url": "https://www.coles.com.au/product/french-fries-potato-chips-multipack-lunch-box-school-snacks-gluten-free-6-pack-111g-6290570",
      "category": "chips-chocolates-snacks",
      "brand": null,
      "weight_size": null,
      "per_unit_price": "$4.05 per 100g",
      "rating": 0,
      "review_count": 0,
      "in_stock": true,
      "is_on_sale": false,
      "scraped_at": "2025-08-06T03:15:08.545Z",
      "page_number": 7,
      "source_url": "https://www.coles.com.au/browse/chips-chocolates-snacks?page=7",
      "is_sponsored": null
    },
    {
      "title": "Europe Nougat Honey Log Chocolate Bar | 40g",
      "current_price": 3,
      "original_price": null,
      "discount_percentage": null,
      "discount_amount": null,
      "image_url": "https://www.coles.com.au/_next/image?url=https%3A%2F%2Fcdn.productimages.coles.com.au%2Fproductimages%2F6%2F67850.jpg&w=640&q=90",
      "product_url": "https://www.coles.com.au/product/europe-nougat-honey-log-chocolate-bar-40g-67850",
      "category": "chips-chocolates-snacks",
      "brand": null,
      "weight_size": null,
      "per_unit_price": "$7.50 per 100g",
      "rating": 0,
      "review_count": 0,
      "in_stock": true,
      "is_on_sale": false,
      "scraped_at": "2025-08-06T03:15:08.545Z",
      "page_number": 7,
      "source_url": "https://www.coles.com.au/browse/chips-chocolates-snacks?page=7",
      "is_sponsored": null
    },
    {
      "title": "Coles Cheese White Rice Crackers | 100g",
      "current_price": 1,
      "original_price": null,
      "discount_percentage": null,
      "discount_amount": null,
      "image_url": "https://www.coles.com.au/_next/image?url=https%3A%2F%2Fcdn.productimages.coles.com.au%2Fproductimages%2F7%2F7908373.jpg&w=640&q=90",
      "product_url": "https://www.coles.com.au/product/coles-cheese-white-rice-crackers-100g-7908373",
      "category": "chips-chocolates-snacks",
      "brand": null,
      "weight_size": null,
      "per_unit_price": "$1.00 per 100g",
      "rating": 0,
      "review_count": 0,
      "in_stock": true,
      "is_on_sale": false,
      "scraped_at": "2025-08-06T03:15:08.545Z",
      "page_number": 7,
      "source_url": "https://www.coles.com.au/browse/chips-chocolates-snacks?page=7",
      "is_sponsored": null
    },
    {
      "title": "Sakata Rice Crackers Wholegrain | 80g",
      "current_price": 2.1,
      "original_price": null,
      "discount_percentage": null,
      "discount_amount": null,
      "image_url": "https://www.coles.com.au/_next/image?url=https%3A%2F%2Fcdn.productimages.coles.com.au%2Fproductimages%2F8%2F8782463.jpg&w=640&q=90",
      "product_url": "https://www.coles.com.au/product/sakata-rice-crackers-wholegrain-80g-8782463",
      "category": "chips-chocolates-snacks",
      "brand": null,
      "weight_size": null,
      "per_unit_price": "$2.63 per 100g",
      "rating": 0,
      "review_count": 0,
      "in_stock": true,
      "is_on_sale": false,
      "scraped_at": "2025-08-06T03:15:08.546Z",
      "page_number": 7,
      "source_url": "https://www.coles.com.au/browse/chips-chocolates-snacks?page=7",
      "is_sponsored": null
    },
    {
      "title": "Arnott's Tiny Teddy Multipack Chocolate 8 Pack | 200g",
      "current_price": 5,
      "original_price": null,
      "discount_percentage": null,
      "discount_amount": null,
      "image_url": "https://www.coles.com.au/_next/image?url=https%3A%2F%2Fcdn.productimages.coles.com.au%2Fproductimages%2F2%2F2992102.jpg&w=640&q=90",
      "product_url": "https://www.coles.com.au/product/arnott's-tiny-teddy-multipack-chocolate-8-pack-200g-2992102",
      "category": "chips-chocolates-snacks",
      "brand": null,
      "weight_size": null,
      "per_unit_price": "$2.50 per 100g",
      "rating": 0,
      "review_count": 0,
      "in_stock": true,
      "is_on_sale": false,
      "scraped_at": "2025-08-06T03:15:08.546Z",
      "page_number": 7,
      "source_url": "https://www.coles.com.au/browse/chips-chocolates-snacks?page=7",
      "is_sponsored": null
    },
    {
      "title": "Nice & Natural Nut Bars Salted Caramel With Dark Choc Multipack Sna ... 180g",
      "current_price": 5.5,
      "original_price": null,
      "discount_percentage": null,
      "discount_amount": null,
      "image_url": "https://www.coles.com.au/_next/image?url=https%3A%2F%2Fcdn.productimages.coles.com.au%2Fproductimages%2F4%2F4288240.jpg&w=640&q=90",
      "product_url": "https://www.coles.com.au/product/nice-and-natural-nut-bars-salted-caramel-with-dark-choc-multipack-snacks-6-pack-180g-4288240",
      "category": "chips-chocolates-snacks",
      "brand": null,
      "weight_size": null,
      "per_unit_price": "$3.06 per 100g",
      "rating": 0,
      "review_count": 0,
      "in_stock": true,
      "is_on_sale": false,
      "scraped_at": "2025-08-06T03:15:08.546Z",
      "page_number": 7,
      "source_url": "https://www.coles.com.au/browse/chips-chocolates-snacks?page=7",
      "is_sponsored": null
    },
    {
      "title": "Thins Onion Rings Original Salted | 85g",
      "current_price": 5,
      "original_price": null,
      "discount_percentage": null,
      "discount_amount": null,
      "image_url": "https://www.coles.com.au/_next/image?url=https%3A%2F%2Fcdn.productimages.coles.com.au%2Fproductimages%2F7%2F7492435.jpg&w=640&q=90",
      "product_url": "https://www.coles.com.au/product/thins-onion-rings-original-salted-85g-7492435",
      "category": "chips-chocolates-snacks",
      "brand": null,
      "weight_size": null,
      "per_unit_price": "$5.88 per 100g",
      "rating": 0,
      "review_count": 0,
      "in_stock": true,
      "is_on_sale": false,
      "scraped_at": "2025-08-06T03:15:08.546Z",
      "page_number": 7,
      "source_url": "https://www.coles.com.au/browse/chips-chocolates-snacks?page=7",
      "is_sponsored": null
    },
    {
      "title": "Lindt Lindor 70% Cocoa Dark Chocolate Balls Bag | 123g",
      "current_price": 13,
      "original_price": null,
      "discount_percentage": null,
      "discount_amount": null,
      "image_url": "https://www.coles.com.au/_next/image?url=https%3A%2F%2Fcdn.productimages.coles.com.au%2Fproductimages%2F2%2F2649584.jpg&w=640&q=90",
      "product_url": "https://www.coles.com.au/product/lindt-lindor-70percent-cocoa-dark-chocolate-balls-bag-123g-2649584",
      "category": "chips-chocolates-snacks",
      "brand": null,
      "weight_size": null,
      "per_unit_price": "$10.57 per 100g",
      "rating": 0,
      "review_count": 0,
      "in_stock": true,
      "is_on_sale": false,
      "scraped_at": "2025-08-06T03:15:08.546Z",
      "page_number": 7,
      "source_url": "https://www.coles.com.au/browse/chips-chocolates-snacks?page=7",
      "is_sponsored": null
    },
    {
      "title": "The Natural Confectionery Co. Jelly Babies Lollies | 220g",
      "current_price": 5,
      "original_price": null,
      "discount_percentage": null,
      "discount_amount": null,
      "image_url": "https://www.coles.com.au/_next/image?url=https%3A%2F%2Fcdn.productimages.coles.com.au%2Fproductimages%2F5%2F5533270.jpg&w=640&q=90",
      "product_url": "https://www.coles.com.au/product/the-natural-confectionery-co.-jelly-babies-lollies-220g-5533270",
      "category": "chips-chocolates-snacks",
      "brand": null,
      "weight_size": null,
      "per_unit_price": "$2.27 per 100g",
      "rating": 0,
      "review_count": 0,
      "in_stock": true,
      "is_on_sale": false,
      "scraped_at": "2025-08-06T03:15:08.546Z",
      "page_number": 7,
      "source_url": "https://www.coles.com.au/browse/chips-chocolates-snacks?page=7",
      "is_sponsored": null
    },
    {
      "title": "Cadbury Twirl Caramilk Chocolate Bites | 130g",
      "current_price": 7,
      "original_price": null,
      "discount_percentage": null,
      "discount_amount": null,
      "image_url": "https://www.coles.com.au/_next/image?url=https%3A%2F%2Fcdn.productimages.coles.com.au%2Fproductimages%2F5%2F5888548.jpg&w=640&q=90",
      "product_url": "https://www.coles.com.au/product/cadbury-twirl-caramilk-chocolate-bites-130g-5888548",
      "category": "chips-chocolates-snacks",
      "brand": null,
      "weight_size": null,
      "per_unit_price": "$5.38 per 100g",
      "rating": 0,
      "review_count": 0,
      "in_stock": true,
      "is_on_sale": false,
      "scraped_at": "2025-08-06T03:15:08.546Z",
      "page_number": 7,
      "source_url": "https://www.coles.com.au/browse/chips-chocolates-snacks?page=7",
      "is_sponsored": null
    },
    {
      "title": "Skittles Fruits Chewy Lollies Snack Tube | 30g",
      "current_price": 2.5,
      "original_price": null,
      "discount_percentage": null,
      "discount_amount": null,
      "image_url": "https://www.coles.com.au/_next/image?url=https%3A%2F%2Fcdn.productimages.coles.com.au%2Fproductimages%2F8%2F8484884.jpg&w=640&q=90",
      "product_url": "https://www.coles.com.au/product/skittles-fruits-chewy-lollies-snack-tube-30g-8484884",
      "category": "chips-chocolates-snacks",
      "brand": null,
      "weight_size": null,
      "per_unit_price": "$8.33 per 100g",
      "rating": 0,
      "review_count": 0,
      "in_stock": true,
      "is_on_sale": false,
      "scraped_at": "2025-08-06T03:15:08.546Z",
      "page_number": 7,
      "source_url": "https://www.coles.com.au/browse/chips-chocolates-snacks?page=7",
      "is_sponsored": null
    },
    {
      "title": "Table Of Plenty Snack Pack Topped Sweet Mini Rice Cakes:milk Choc | 84g",
      "current_price": 7,
      "original_price": null,
      "discount_percentage": null,
      "discount_amount": null,
      "image_url": "https://www.coles.com.au/_next/image?url=https%3A%2F%2Fcdn.productimages.coles.com.au%2Fproductimages%2F8%2F8712504.jpg&w=640&q=90",
      "product_url": "https://www.coles.com.au/product/table-of-plenty-snack-pack-topped-sweet-mini-rice-cakes:milk-choc-84g-8712504",
      "category": "chips-chocolates-snacks",
      "brand": null,
      "weight_size": null,
      "per_unit_price": "$8.33 per 100g",
      "rating": 0,
      "review_count": 0,
      "in_stock": true,
      "is_on_sale": false,
      "scraped_at": "2025-08-06T03:15:08.546Z",
      "page_number": 7,
      "source_url": "https://www.coles.com.au/browse/chips-chocolates-snacks?page=7",
      "is_sponsored": null
    },
    {
      "title": "Pringles Potato Chips Caribbean Spiced Chicken | 118g",
      "current_price": 5.5,
      "original_price": null,
      "discount_percentage": null,
      "discount_amount": null,
      "image_url": "https://www.coles.com.au/_next/image?url=https%3A%2F%2Fcdn.productimages.coles.com.au%2Fproductimages%2F9%2F9054360.jpg&w=640&q=90",
      "product_url": "https://www.coles.com.au/product/pringles-potato-chips-caribbean-spiced-chicken-118g-9054360",
      "category": "chips-chocolates-snacks",
      "brand": null,
      "weight_size": null,
      "per_unit_price": "$4.66 per 100g",
      "rating": 0,
      "review_count": 0,
      "in_stock": true,
      "is_on_sale": false,
      "scraped_at": "2025-08-06T03:15:08.546Z",
      "page_number": 7,
      "source_url": "https://www.coles.com.au/browse/chips-chocolates-snacks?page=7",
      "is_sponsored": null
    },
    {
      "title": "Sour Patch Kids Layers. | 190GRAM",
      "current_price": 5,
      "original_price": null,
      "discount_percentage": null,
      "discount_amount": null,
      "image_url": "https://www.coles.com.au/_next/image?url=https%3A%2F%2Fcdn.productimages.coles.com.au%2Fproductimages%2F9%2F9056853.jpg&w=640&q=90",
      "product_url": "https://www.coles.com.au/product/sour-patch-kids-layers.-190gram-9056853",
      "category": "chips-chocolates-snacks",
      "brand": null,
      "weight_size": null,
      "per_unit_price": "$2.63 per 100g",
      "rating": 0,
      "review_count": 0,
      "in_stock": true,
      "is_on_sale": false,
      "scraped_at": "2025-08-06T03:15:08.546Z",
      "page_number": 7,
      "source_url": "https://www.coles.com.au/browse/chips-chocolates-snacks?page=7",
      "is_sponsored": null
    },
    {
      "title": "Captain's Table Classic Water Crackers | 125g",
      "current_price": 2.2,
      "original_price": null,
      "discount_percentage": null,
      "discount_amount": null,
      "image_url": "https://www.coles.com.au/_next/image?url=https%3A%2F%2Fcdn.productimages.coles.com.au%2Fproductimages%2F8%2F8842022.jpg&w=640&q=90",
      "product_url": "https://www.coles.com.au/product/captain's-table-classic-water-crackers-125g-8842022",
      "category": "chips-chocolates-snacks",
      "brand": null,
      "weight_size": null,
      "per_unit_price": "$1.76 per 100g",
      "rating": 0,
      "review_count": 0,
      "in_stock": true,
      "is_on_sale": false,
      "scraped_at": "2025-08-06T03:15:08.546Z",
      "page_number": 7,
      "source_url": "https://www.coles.com.au/browse/chips-chocolates-snacks?page=7",
      "is_sponsored": null
    },
    {
      "title": "Arnott's Shapes Cracker Biscuits Original Barbecue Multipack 8 Pack | 200g",
      "current_price": 5,
      "original_price": null,
      "discount_percentage": null,
      "discount_amount": null,
      "image_url": "https://www.coles.com.au/_next/image?url=https%3A%2F%2Fcdn.productimages.coles.com.au%2Fproductimages%2F2%2F2992215.jpg&w=640&q=90",
      "product_url": "https://www.coles.com.au/product/arnott's-shapes-cracker-biscuits-original-barbecue-multipack-8-pack-200g-2992215",
      "category": "chips-chocolates-snacks",
      "brand": null,
      "weight_size": null,
      "per_unit_price": "$2.50 per 100g",
      "rating": 0,
      "review_count": 0,
      "in_stock": true,
      "is_on_sale": false,
      "scraped_at": "2025-08-06T03:15:08.546Z",
      "page_number": 7,
      "source_url": "https://www.coles.com.au/browse/chips-chocolates-snacks?page=7",
      "is_sponsored": null
    },
    {
      "title": "Cadbury Freddo Milk Chocolate Dipped Biscuits | 167g",
      "current_price": 5.5,
      "original_price": null,
      "discount_percentage": null,
      "discount_amount": null,
      "image_url": "https://www.coles.com.au/_next/image?url=https%3A%2F%2Fcdn.productimages.coles.com.au%2Fproductimages%2F3%2F3265792.jpg&w=640&q=90",
      "product_url": "https://www.coles.com.au/product/cadbury-freddo-milk-chocolate-dipped-biscuits-167g-3265792",
      "category": "chips-chocolates-snacks",
      "brand": null,
      "weight_size": null,
      "per_unit_price": "$3.29 per 100g",
      "rating": 0,
      "review_count": 0,
      "in_stock": true,
      "is_on_sale": false,
      "scraped_at": "2025-08-06T03:15:08.546Z",
      "page_number": 7,
      "source_url": "https://www.coles.com.au/browse/chips-chocolates-snacks?page=7",
      "is_sponsored": null
    },
    {
      "title": "Cadbury Dream Oreo White Chocolate Block | 170g",
      "current_price": 8,
      "original_price": null,
      "discount_percentage": null,
      "discount_amount": null,
      "image_url": "https://www.coles.com.au/_next/image?url=https%3A%2F%2Fcdn.productimages.coles.com.au%2Fproductimages%2F5%2F5856520.jpg&w=640&q=90",
      "product_url": "https://www.coles.com.au/product/cadbury-dream-oreo-white-chocolate-block-170g-5856520",
      "category": "chips-chocolates-snacks",
      "brand": null,
      "weight_size": null,
      "per_unit_price": "$4.71 per 100g",
      "rating": 0,
      "review_count": 0,
      "in_stock": true,
      "is_on_sale": false,
      "scraped_at": "2025-08-06T03:15:08.546Z",
      "page_number": 7,
      "source_url": "https://www.coles.com.au/browse/chips-chocolates-snacks?page=7",
      "is_sponsored": null
    },
    {
      "title": "Table Of Plenty Snack Pack Topped Sweet Mini Rice Cakes:dark Choc | 84g",
      "current_price": 7,
      "original_price": null,
      "discount_percentage": null,
      "discount_amount": null,
      "image_url": "https://www.coles.com.au/_next/image?url=https%3A%2F%2Fcdn.productimages.coles.com.au%2Fproductimages%2F8%2F8712515.jpg&w=640&q=90",
      "product_url": "https://www.coles.com.au/product/table-of-plenty-snack-pack-topped-sweet-mini-rice-cakes:dark-choc-84g-8712515",
      "category": "chips-chocolates-snacks",
      "brand": null,
      "weight_size": null,
      "per_unit_price": "$8.33 per 100g",
      "rating": 0,
      "review_count": 0,
      "in_stock": true,
      "is_on_sale": false,
      "scraped_at": "2025-08-06T03:15:08.546Z",
      "page_number": 7,
      "source_url": "https://www.coles.com.au/browse/chips-chocolates-snacks?page=7",
      "is_sponsored": null
    },
    {
      "title": "Lindt Lindor Strawberries & Cream White Chocolate Bag | 125g",
      "current_price": 13,
      "original_price": null,
      "discount_percentage": null,
      "discount_amount": null,
      "image_url": "https://www.coles.com.au/_next/image?url=https%3A%2F%2Fcdn.productimages.coles.com.au%2Fproductimages%2F1%2F1823573.jpg&w=640&q=90",
      "product_url": "https://www.coles.com.au/product/lindt-lindor-strawberries-and-cream-white-chocolate-bag-125g-1823573",
      "category": "chips-chocolates-snacks",
      "brand": null,
      "weight_size": null,
      "per_unit_price": "$10.40 per 100g",
      "rating": 5,
      "review_count": 2,
      "in_stock": true,
      "is_on_sale": false,
      "scraped_at": "2025-08-06T03:15:08.546Z",
      "page_number": 7,
      "source_url": "https://www.coles.com.au/browse/chips-chocolates-snacks?page=7",
      "is_sponsored": null
    },
    {
      "title": "Mars Raspberry Smash Flavoured Chocolate Bar | 47g",
      "current_price": 2.5,
      "original_price": null,
      "discount_percentage": null,
      "discount_amount": null,
      "image_url": "https://www.coles.com.au/_next/image?url=https%3A%2F%2Fcdn.productimages.coles.com.au%2Fproductimages%2F8%2F8425648.jpg&w=640&q=90",
      "product_url": "https://www.coles.com.au/product/mars-raspberry-smash-flavoured-chocolate-bar-47g-8425648",
      "category": "chips-chocolates-snacks",
      "brand": null,
      "weight_size": null,
      "per_unit_price": "$5.32 per 100g",
      "rating": 0,
      "review_count": 0,
      "in_stock": true,
      "is_on_sale": false,
      "scraped_at": "2025-08-06T03:15:08.546Z",
      "page_number": 7,
      "source_url": "https://www.coles.com.au/browse/chips-chocolates-snacks?page=7",
      "is_sponsored": null
    },
    {
      "title": "The Natural Confect Co. 50% Less Sugar Snakes | 130g",
      "current_price": 5,
      "original_price": null,
      "discount_percentage": null,
      "discount_amount": null,
      "image_url": "https://www.coles.com.au/_next/image?url=https%3A%2F%2Fcdn.productimages.coles.com.au%2Fproductimages%2F8%2F8544217.jpg&w=640&q=90",
      "product_url": "https://www.coles.com.au/product/the-natural-confect-co.-50percent-less-sugar-snakes-130g-8544217",
      "category": "chips-chocolates-snacks",
      "brand": null,
      "weight_size": null,
      "per_unit_price": "$3.85 per 100g",
      "rating": 0,
      "review_count": 0,
      "in_stock": true,
      "is_on_sale": false,
      "scraped_at": "2025-08-06T03:15:08.546Z",
      "page_number": 7,
      "source_url": "https://www.coles.com.au/browse/chips-chocolates-snacks?page=7",
      "is_sponsored": null
    },
    {
      "title": "Lindt Lindor Raspberry & Cream Chocolate Bag | 123GRAM",
      "current_price": 13,
      "original_price": null,
      "discount_percentage": null,
      "discount_amount": null,
      "image_url": "https://www.coles.com.au/_next/image?url=https%3A%2F%2Fcdn.productimages.coles.com.au%2Fproductimages%2F9%2F9043170.jpg&w=640&q=90",
      "product_url": "https://www.coles.com.au/product/lindt-lindor-raspberry-and-cream-chocolate-bag-123gram-9043170",
      "category": "chips-chocolates-snacks",
      "brand": null,
      "weight_size": null,
      "per_unit_price": "$10.57 per 100g",
      "rating": 0,
      "review_count": 0,
      "in_stock": true,
      "is_on_sale": false,
      "scraped_at": "2025-08-06T03:15:08.546Z",
      "page_number": 7,
      "source_url": "https://www.coles.com.au/browse/chips-chocolates-snacks?page=7",
      "is_sponsored": null
    },
    {
      "title": "Red Rock Deli Potato Chips Multipack Of 5 Sweet Chili & Sour Cream | 140g",
      "current_price": 5.75,
      "original_price": null,
      "discount_percentage": null,
      "discount_amount": null,
      "image_url": "https://www.coles.com.au/_next/image?url=https%3A%2F%2Fcdn.productimages.coles.com.au%2Fproductimages%2F3%2F3995784.jpg&w=640&q=90",
      "product_url": "https://www.coles.com.au/product/red-rock-deli-potato-chips-multipack-of-5-sweet-chili-and-sour-cream-140g-3995784",
      "category": "chips-chocolates-snacks",
      "brand": null,
      "weight_size": null,
      "per_unit_price": "$4.11 per 100g",
      "rating": 4.6,
      "review_count": 77,
      "in_stock": true,
      "is_on_sale": false,
      "scraped_at": "2025-08-06T03:15:08.546Z",
      "page_number": 7,
      "source_url": "https://www.coles.com.au/browse/chips-chocolates-snacks?page=7",
      "is_sponsored": null
    },
    {
      "title": "Cadbury Dream White Chocolate Block | 180g",
      "current_price": 8,
      "original_price": null,
      "discount_percentage": null,
      "discount_amount": null,
      "image_url": "https://www.coles.com.au/_next/image?url=https%3A%2F%2Fcdn.productimages.coles.com.au%2Fproductimages%2F2%2F2351684.jpg&w=640&q=90",
      "product_url": "https://www.coles.com.au/product/cadbury-dream-white-chocolate-block-180g-2351684",
      "category": "chips-chocolates-snacks",
      "brand": null,
      "weight_size": null,
      "per_unit_price": "$4.44 per 100g",
      "rating": 0,
      "review_count": 0,
      "in_stock": true,
      "is_on_sale": false,
      "scraped_at": "2025-08-06T03:15:08.546Z",
      "page_number": 7,
      "source_url": "https://www.coles.com.au/browse/chips-chocolates-snacks?page=7",
      "is_sponsored": null
    },
    {
      "title": "Cadbury Caramilk Marvellous Creations Chocolate Block | 190g",
      "current_price": 8,
      "original_price": null,
      "discount_percentage": null,
      "discount_amount": null,
      "image_url": "https://www.coles.com.au/_next/image?url=https%3A%2F%2Fcdn.productimages.coles.com.au%2Fproductimages%2F6%2F6338870.jpg&w=640&q=90",
      "product_url": "https://www.coles.com.au/product/cadbury-caramilk-marvellous-creations-chocolate-block-190g-6338870",
      "category": "chips-chocolates-snacks",
      "brand": null,
      "weight_size": null,
      "per_unit_price": "$4.21 per 100g",
      "rating": 0,
      "review_count": 0,
      "in_stock": true,
      "is_on_sale": false,
      "scraped_at": "2025-08-06T03:15:08.546Z",
      "page_number": 7,
      "source_url": "https://www.coles.com.au/browse/chips-chocolates-snacks?page=7",
      "is_sponsored": null
    },
    {
      "title": "Sakata Rice Cracker Biscuits Cheese | 90g",
      "current_price": 2.1,
      "original_price": null,
      "discount_percentage": null,
      "discount_amount": null,
      "image_url": "https://www.coles.com.au/_next/image?url=https%3A%2F%2Fcdn.productimages.coles.com.au%2Fproductimages%2F8%2F8782099.jpg&w=640&q=90",
      "product_url": "https://www.coles.com.au/product/sakata-rice-cracker-biscuits-cheese-90g-8782099",
      "category": "chips-chocolates-snacks",
      "brand": null,
      "weight_size": null,
      "per_unit_price": "$2.33 per 100g",
      "rating": 0,
      "review_count": 0,
      "in_stock": true,
      "is_on_sale": false,
      "scraped_at": "2025-08-06T03:15:08.546Z",
      "page_number": 7,
      "source_url": "https://www.coles.com.au/browse/chips-chocolates-snacks?page=7",
      "is_sponsored": null
    },
    {
      "title": "Cadbury Caramilk Marble Chocolate Block | 173g",
      "current_price": 8,
      "original_price": null,
      "discount_percentage": null,
      "discount_amount": null,
      "image_url": "https://www.coles.com.au/_next/image?url=https%3A%2F%2Fcdn.productimages.coles.com.au%2Fproductimages%2F4%2F4150140.jpg&w=640&q=90",
      "product_url": "https://www.coles.com.au/product/cadbury-caramilk-marble-chocolate-block-173g-4150140",
      "category": "chips-chocolates-snacks",
      "brand": null,
      "weight_size": null,
      "per_unit_price": "$4.62 per 100g",
      "rating": 0,
      "review_count": 0,
      "in_stock": true,
      "is_on_sale": false,
      "scraped_at": "2025-08-06T03:15:08.546Z",
      "page_number": 7,
      "source_url": "https://www.coles.com.au/browse/chips-chocolates-snacks?page=7",
      "is_sponsored": null
    },
    {
      "title": "Chickadees Chicken Chips Multipack Lunch Box School Snacks 6 Pack | 114g",
      "current_price": 4.5,
      "original_price": null,
      "discount_percentage": null,
      "discount_amount": null,
      "image_url": "https://www.coles.com.au/_next/image?url=https%3A%2F%2Fcdn.productimages.coles.com.au%2Fproductimages%2F4%2F4467238.jpg&w=640&q=90",
      "product_url": "https://www.coles.com.au/product/chickadees-chicken-chips-multipack-lunch-box-school-snacks-6-pack-114g-4467238",
      "category": "chips-chocolates-snacks",
      "brand": null,
      "weight_size": null,
      "per_unit_price": "$3.95 per 100g",
      "rating": 0,
      "review_count": 0,
      "in_stock": true,
      "is_on_sale": false,
      "scraped_at": "2025-08-06T03:15:08.546Z",
      "page_number": 7,
      "source_url": "https://www.coles.com.au/browse/chips-chocolates-snacks?page=7",
      "is_sponsored": null
    },
    {
      "title": "Gumi Yum Surprise Series 1 Blue | 21g",
      "current_price": 3,
      "original_price": null,
      "discount_percentage": null,
      "discount_amount": null,
      "image_url": "https://www.coles.com.au/_next/image?url=https%3A%2F%2Fcdn.productimages.coles.com.au%2Fproductimages%2F6%2F6344975.jpg&w=640&q=90",
      "product_url": "https://www.coles.com.au/product/gumi-yum-surprise-series-1-blue-21g-6344975",
      "category": "chips-chocolates-snacks",
      "brand": null,
      "weight_size": null,
      "per_unit_price": "$14.29 per 100g",
      "rating": 0,
      "review_count": 0,
      "in_stock": true,
      "is_on_sale": false,
      "scraped_at": "2025-08-06T03:15:08.546Z",
      "page_number": 7,
      "source_url": "https://www.coles.com.au/browse/chips-chocolates-snacks?page=7",
      "is_sponsored": null
    },
    {
      "title": "Lindt Lindor Cheesecake Chocolate Bag | 123g",
      "current_price": 13,
      "original_price": null,
      "discount_percentage": null,
      "discount_amount": null,
      "image_url": "https://www.coles.com.au/_next/image?url=https%3A%2F%2Fcdn.productimages.coles.com.au%2Fproductimages%2F7%2F7669228.jpg&w=640&q=90",
      "product_url": "https://www.coles.com.au/product/lindt-lindor-cheesecake-chocolate-bag-123g-7669228",
      "category": "chips-chocolates-snacks",
      "brand": null,
      "weight_size": null,
      "per_unit_price": "$10.57 per 100g",
      "rating": 4.8,
      "review_count": 5,
      "in_stock": true,
      "is_on_sale": false,
      "scraped_at": "2025-08-06T03:15:08.546Z",
      "page_number": 7,
      "source_url": "https://www.coles.com.au/browse/chips-chocolates-snacks?page=7",
      "is_sponsored": null
    },
    {
      "title": "Thins Onion Rings Sweet Chilli Sour | 85g",
      "current_price": 5,
      "original_price": null,
      "discount_percentage": null,
      "discount_amount": null,
      "image_url": "https://www.coles.com.au/_next/image?url=https%3A%2F%2Fcdn.productimages.coles.com.au%2Fproductimages%2F8%2F8446116.jpg&w=640&q=90",
      "product_url": "https://www.coles.com.au/product/thins-onion-rings-sweet-chilli-sour-85g-8446116",
      "category": "chips-chocolates-snacks",
      "brand": null,
      "weight_size": null,
      "per_unit_price": "$5.88 per 100g",
      "rating": 0,
      "review_count": 0,
      "in_stock": true,
      "is_on_sale": false,
      "scraped_at": "2025-08-06T03:15:08.546Z",
      "page_number": 7,
      "source_url": "https://www.coles.com.au/browse/chips-chocolates-snacks?page=7",
      "is_sponsored": null
    },
    {
      "title": "Cadbury Sticky Toffee Slice | 178g",
      "current_price": 8,
      "original_price": null,
      "discount_percentage": null,
      "discount_amount": null,
      "image_url": "https://www.coles.com.au/_next/image?url=https%3A%2F%2Fcdn.productimages.coles.com.au%2Fproductimages%2F9%2F9960884.jpg&w=640&q=90",
      "product_url": "https://www.coles.com.au/product/cadbury-sticky-toffee-slice-178g-9960884",
      "category": "chips-chocolates-snacks",
      "brand": null,
      "weight_size": null,
      "per_unit_price": "$4.49 per 100g",
      "rating": 0,
      "review_count": 0,
      "in_stock": true,
      "is_on_sale": false,
      "scraped_at": "2025-08-06T03:15:08.546Z",
      "page_number": 7,
      "source_url": "https://www.coles.com.au/browse/chips-chocolates-snacks?page=7",
      "is_sponsored": null
    },
    {
      "title": "Oreo Mini Original Cookies Sharepack | 157g",
      "current_price": 4.5,
      "original_price": null,
      "discount_percentage": null,
      "discount_amount": null,
      "image_url": "https://www.coles.com.au/_next/image?url=https%3A%2F%2Fcdn.productimages.coles.com.au%2Fproductimages%2F5%2F5605304.jpg&w=640&q=90",
      "product_url": "https://www.coles.com.au/product/oreo-mini-original-cookies-sharepack-157g-5605304",
      "category": "chips-chocolates-snacks",
      "brand": null,
      "weight_size": null,
      "per_unit_price": "$2.87 per 100g",
      "rating": 0,
      "review_count": 0,
      "in_stock": true,
      "is_on_sale": false,
      "scraped_at": "2025-08-06T03:15:08.546Z",
      "page_number": 7,
      "source_url": "https://www.coles.com.au/browse/chips-chocolates-snacks?page=7",
      "is_sponsored": null
    },
    {
      "title": "Lindor Tiramisu Bag | 123g",
      "current_price": 13,
      "original_price": null,
      "discount_percentage": null,
      "discount_amount": null,
      "image_url": "https://www.coles.com.au/_next/image?url=https%3A%2F%2Fcdn.productimages.coles.com.au%2Fproductimages%2F1%2F1112393.jpg&w=640&q=90",
      "product_url": "https://www.coles.com.au/product/lindor-tiramisu-bag-123g-1112393",
      "category": "chips-chocolates-snacks",
      "brand": null,
      "weight_size": null,
      "per_unit_price": "$10.57 per 100g",
      "rating": 0,
      "review_count": 0,
      "in_stock": true,
      "is_on_sale": false,
      "scraped_at": "2025-08-06T03:15:08.546Z",
      "page_number": 7,
      "source_url": "https://www.coles.com.au/browse/chips-chocolates-snacks?page=7",
      "is_sponsored": null
    },
    {
      "title": "Lindt Lindor Milk Salted Caramel Chocolate Bag | 123g",
      "current_price": 13,
      "original_price": null,
      "discount_percentage": null,
      "discount_amount": null,
      "image_url": "https://www.coles.com.au/_next/image?url=https%3A%2F%2Fcdn.productimages.coles.com.au%2Fproductimages%2F4%2F4841378.jpg&w=640&q=90",
      "product_url": "https://www.coles.com.au/product/lindt-lindor-milk-salted-caramel-chocolate-bag-123g-4841378",
      "category": "chips-chocolates-snacks",
      "brand": null,
      "weight_size": null,
      "per_unit_price": "$10.57 per 100g",
      "rating": 0,
      "review_count": 0,
      "in_stock": true,
      "is_on_sale": false,
      "scraped_at": "2025-08-06T03:15:08.546Z",
      "page_number": 7,
      "source_url": "https://www.coles.com.au/browse/chips-chocolates-snacks?page=7",
      "is_sponsored": null
    },
    {
      "title": "Cadbury Dairy Milk Triple Decker Mint Chocolate Block | 178g",
      "current_price": 8,
      "original_price": null,
      "discount_percentage": null,
      "discount_amount": null,
      "image_url": "https://www.coles.com.au/_next/image?url=https%3A%2F%2Fcdn.productimages.coles.com.au%2Fproductimages%2F6%2F6544963.jpg&w=640&q=90",
      "product_url": "https://www.coles.com.au/product/cadbury-dairy-milk-triple-decker-mint-chocolate-block-178g-6544963",
      "category": "chips-chocolates-snacks",
      "brand": null,
      "weight_size": null,
      "per_unit_price": "$4.49 per 100g",
      "rating": 0,
      "review_count": 0,
      "in_stock": true,
      "is_on_sale": false,
      "scraped_at": "2025-08-06T03:15:08.546Z",
      "page_number": 7,
      "source_url": "https://www.coles.com.au/browse/chips-chocolates-snacks?page=7",
      "is_sponsored": null
    },
    {
      "title": "Cadbury Dairy Milk Turkish Delight Chocolate Block | 180g",
      "current_price": 8,
      "original_price": null,
      "discount_percentage": null,
      "discount_amount": null,
      "image_url": "https://www.coles.com.au/_next/image?url=https%3A%2F%2Fcdn.productimages.coles.com.au%2Fproductimages%2F2%2F2351593.jpg&w=640&q=90",
      "product_url": "https://www.coles.com.au/product/cadbury-dairy-milk-turkish-delight-chocolate-block-180g-2351593",
      "category": "chips-chocolates-snacks",
      "brand": null,
      "weight_size": null,
      "per_unit_price": "$4.44 per 100g",
      "rating": 0,
      "review_count": 0,
      "in_stock": true,
      "is_on_sale": false,
      "scraped_at": "2025-08-06T03:15:08.546Z",
      "page_number": 7,
      "source_url": "https://www.coles.com.au/browse/chips-chocolates-snacks?page=7",
      "is_sponsored": null
    }
  ],
  "summary": {
    "total_products": 58,
    "products_on_sale": 0,
    "products_with_ratings": 58,
    "average_price": 6.309482758620691,
    "price_range": {
      "min": 1,
      "max": 13
    }
  }
}